<?xml version="1.0" encoding="UTF-8" standalone="yes"?>
<w:styles xmlns:wpc="http://schemas.microsoft.com/office/word/2010/wordprocessingCanvas" xmlns:mc="http://schemas.openxmlformats.org/markup-compatibility/2006" xmlns:o="urn:schemas-microsoft-com:office:office" xmlns:r="http://schemas.openxmlformats.org/officeDocument/2006/relationships" xmlns:m="http://schemas.openxmlformats.org/officeDocument/2006/math" xmlns:v="urn:schemas-microsoft-com:vml" xmlns:wp14="http://schemas.microsoft.com/office/word/2010/wordprocessingDrawing" xmlns:wp="http://schemas.openxmlformats.org/drawingml/2006/wordprocessingDrawing" xmlns:w10="urn:schemas-microsoft-com:office:word" xmlns:w="http://schemas.openxmlformats.org/wordprocessingml/2006/main" xmlns:w14="http://schemas.microsoft.com/office/word/2010/wordml" xmlns:wpg="http://schemas.microsoft.com/office/word/2010/wordprocessingGroup" xmlns:wpi="http://schemas.microsoft.com/office/word/2010/wordprocessingInk" xmlns:wne="http://schemas.microsoft.com/office/word/2006/wordml" xmlns:wps="http://schemas.microsoft.com/office/word/2010/wordprocessingShape" mc:Ignorable="w14 wp14"><w:docDefaults><w:rPrDefault><w:rPr><w:rFonts w:asciiTheme="minorHAnsi" w:eastAsiaTheme="minorEastAsia" w:hAnsiTheme="minorHAnsi" w:cstheme="minorBidi"/><w:kern w:val="2"/><w:sz w:val="21"/><w:szCs w:val="22"/><w:lang w:val="en-US" w:eastAsia="zh-CN" w:bidi="ar-SA"/></w:rPr></w:rPrDefault><w:pPrDefault/></w:docDefaults><w:latentStyles w:defLockedState="0" w:defUIPriority="99" w:defSemiHidden="1" w:defUnhideWhenUsed="1" w:defQFormat="0" w:count="267"><w:lsdException w:name="Normal" w:semiHidden="0" w:uiPriority="0" w:unhideWhenUsed="0" w:qFormat="1"/><w:lsdException w:name="heading 1" w:semiHidden="0" w:uiPriority="9" w:unhideWhenUsed="0" w:qFormat="1"/><w:lsdException w:name="heading 2" w:uiPriority="9" w:qFormat="1"/><w:lsdException w:name="heading 3" w:uiPriority="9" w:qFormat="1"/><w:lsdException w:name="heading 4" w:uiPriority="9" w:qFormat="1"/><w:lsdException w:name="heading 5" w:uiPriority="9" w:qFormat="1"/><w:lsdException w:name="heading 6" w:uiPriority="9" w:qFormat="1"/><w:lsdException w:name="heading 7" w:uiPriority="9" w:qFormat="1"/><w:lsdException w:name="heading 8" w:uiPriority="9" w:qFormat="1"/><w:lsdException w:name="heading 9" w:uiPriority="9" w:qFormat="1"/><w:lsdException w:name="toc 1" w:uiPriority="39"/><w:lsdException w:name="toc 2" w:uiPriority="39"/><w:lsdException w:name="toc 3" w:uiPriority="39"/><w:lsdException w:name="toc 4" w:uiPriority="39"/><w:lsdException w:name="toc 5" w:uiPriority="39"/><w:lsdException w:name="toc 6" w:uiPriority="39"/><w:lsdException w:name="toc 7" w:uiPriority="39"/><w:lsdException w:name="toc 8" w:uiPriority="39"/><w:lsdException w:name="toc 9" w:uiPriority="39"/><w:lsdException w:name="caption" w:uiPriority="35" w:qFormat="1"/><w:lsdException w:name="Title" w:semiHidden="0" w:uiPriority="10" w:unhideWhenUsed="0" w:qFormat="1"/><w:lsdException w:name="Default Paragraph Font" w:uiPriority="1"/><w:lsdException w:name="Subtitle" w:semiHidden="0" w:uiPriority="11" w:unhideWhenUsed="0" w:qFormat="1"/><w:lsdException w:name="Strong" w:semiHidden="0" w:uiPriority="22" w:unhideWhenUsed="0" w:qFormat="1"/><w:lsdException w:name="Emphasis" w:semiHidden="0" w:uiPriority="20" w:unhideWhenUsed="0" w:qFormat="1"/><w:lsdException w:name="Normal (Web)" w:qFormat="1"/><w:lsdException w:name="Table Grid" w:semiHidden="0" w:uiPriority="39" w:unhideWhenUsed="0"/><w:lsdException w:name="Placeholder Text" w:unhideWhenUsed="0"/><w:lsdException w:name="No Spacing" w:semiHidden="0" w:uiPriority="1" w:unhideWhenUsed="0" w:qFormat="1"/><w:lsdException w:name="Light Shading" w:semiHidden="0" w:uiPriority="60" w:unhideWhenUsed="0"/><w:lsdException w:name="Light List" w:semiHidden="0" w:uiPriority="61" w:unhideWhenUsed="0"/><w:lsdException w:name="Light Grid" w:semiHidden="0" w:uiPriority="62" w:unhideWhenUsed="0"/><w:lsdException w:name="Medium Shading 1" w:semiHidden="0" w:uiPriority="63" w:unhideWhenUsed="0"/><w:lsdException w:name="Medium Shading 2" w:semiHidden="0" w:uiPriority="64" w:unhideWhenUsed="0"/><w:lsdException w:name="Medium List 1" w:semiHidden="0" w:uiPriority="65" w:unhideWhenUsed="0"/><w:lsdException w:name="Medium List 2" w:semiHidden="0" w:uiPriority="66" w:unhideWhenUsed="0"/><w:lsdException w:name="Medium Grid 1" w:semiHidden="0" w:uiPriority="67" w:unhideWhenUsed="0"/><w:lsdException w:name="Medium Grid 2" w:semiHidden="0" w:uiPriority="68" w:unhideWhenUsed="0"/><w:lsdException w:name="Medium Grid 3" w:semiHidden="0" w:uiPriority="69" w:unhideWhenUsed="0"/><w:lsdException w:name="Dark List" w:semiHidden="0" w:uiPriority="70" w:unhideWhenUsed="0"/><w:lsdException w:name="Colorful Shading" w:semiHidden="0" w:uiPriority="71" w:unhideWhenUsed="0"/><w:lsdException w:name="Colorful List" w:semiHidden="0" w:uiPriority="72" w:unhideWhenUsed="0"/><w:lsdException w:name="Colorful Grid" w:semiHidden="0" w:uiPriority="73" w:unhideWhenUsed="0"/><w:lsdException w:name="Light Shading Accent 1" w:semiHidden="0" w:uiPriority="60" w:unhideWhenUsed="0"/><w:lsdException w:name="Light List Accent 1" w:semiHidden="0" w:uiPriority="61" w:unhideWhenUsed="0"/><w:lsdException w:name="Light Grid Accent 1" w:semiHidden="0" w:uiPriority="62" w:unhideWhenUsed="0"/><w:lsdException w:name="Medium Shading 1 Accent 1" w:semiHidden="0" w:uiPriority="63" w:unhideWhenUsed="0"/><w:lsdException w:name="Medium Shading 2 Accent 1" w:semiHidden="0" w:uiPriority="64" w:unhideWhenUsed="0"/><w:lsdException w:name="Medium List 1 Accent 1" w:semiHidden="0" w:uiPriority="65" w:unhideWhenUsed="0"/><w:lsdException w:name="Revision" w:unhideWhenUsed="0"/><w:lsdException w:name="List Paragraph" w:semiHidden="0" w:uiPriority="34" w:unhideWhenUsed="0" w:qFormat="1"/><w:lsdException w:name="Quote" w:semiHidden="0" w:uiPriority="29" w:unhideWhenUsed="0" w:qFormat="1"/><w:lsdException w:name="Intense Quote" w:semiHidden="0" w:uiPriority="30" w:unhideWhenUsed="0" w:qFormat="1"/><w:lsdException w:name="Medium List 2 Accent 1" w:semiHidden="0" w:uiPriority="66" w:unhideWhenUsed="0"/><w:lsdException w:name="Medium Grid 1 Accent 1" w:semiHidden="0" w:uiPriority="67" w:unhideWhenUsed="0"/><w:lsdException w:name="Medium Grid 2 Accent 1" w:semiHidden="0" w:uiPriority="68" w:unhideWhenUsed="0"/><w:lsdException w:name="Medium Grid 3 Accent 1" w:semiHidden="0" w:uiPriority="69" w:unhideWhenUsed="0"/><w:lsdException w:name="Dark List Accent 1" w:semiHidden="0" w:uiPriority="70" w:unhideWhenUsed="0"/><w:lsdException w:name="Colorful Shading Accent 1" w:semiHidden="0" w:uiPriority="71" w:unhideWhenUsed="0"/><w:lsdException w:name="Colorful List Accent 1" w:semiHidden="0" w:uiPriority="72" w:unhideWhenUsed="0"/><w:lsdException w:name="Colorful Grid Accent 1" w:semiHidden="0" w:uiPriority="73" w:unhideWhenUsed="0"/><w:lsdException w:name="Light Shading Accent 2" w:semiHidden="0" w:uiPriority="60" w:unhideWhenUsed="0"/><w:lsdException w:name="Light List Accent 2" w:semiHidden="0" w:uiPriority="61" w:unhideWhenUsed="0"/><w:lsdException w:name="Light Grid Accent 2" w:semiHidden="0" w:uiPriority="62" w:unhideWhenUsed="0"/><w:lsdException w:name="Medium Shading 1 Accent 2" w:semiHidden="0" w:uiPriority="63" w:unhideWhenUsed="0"/><w:lsdException w:name="Medium Shading 2 Accent 2" w:semiHidden="0" w:uiPriority="64" w:unhideWhenUsed="0"/><w:lsdException w:name="Medium List 1 Accent 2" w:semiHidden="0" w:uiPriority="65" w:unhideWhenUsed="0"/><w:lsdException w:name="Medium List 2 Accent 2" w:semiHidden="0" w:uiPriority="66" w:unhideWhenUsed="0"/><w:lsdException w:name="Medium Grid 1 Accent 2" w:semiHidden="0" w:uiPriority="67" w:unhideWhenUsed="0"/><w:lsdException w:name="Medium Grid 2 Accent 2" w:semiHidden="0" w:uiPriority="68" w:unhideWhenUsed="0"/><w:lsdException w:name="Medium Grid 3 Accent 2" w:semiHidden="0" w:uiPriority="69" w:unhideWhenUsed="0"/><w:lsdException w:name="Dark List Accent 2" w:semiHidden="0" w:uiPriority="70" w:unhideWhenUsed="0"/><w:lsdException w:name="Colorful Shading Accent 2" w:semiHidden="0" w:uiPriority="71" w:unhideWhenUsed="0"/><w:lsdException w:name="Colorful List Accent 2" w:semiHidden="0" w:uiPriority="72" w:unhideWhenUsed="0"/><w:lsdException w:name="Colorful Grid Accent 2" w:semiHidden="0" w:uiPriority="73" w:unhideWhenUsed="0"/><w:lsdException w:name="Light Shading Accent 3" w:semiHidden="0" w:uiPriority="60" w:unhideWhenUsed="0"/><w:lsdException w:name="Light List Accent 3" w:semiHidden="0" w:uiPriority="61" w:unhideWhenUsed="0"/><w:lsdException w:name="Light Grid Accent 3" w:semiHidden="0" w:uiPriority="62" w:unhideWhenUsed="0"/><w:lsdException w:name="Medium Shading 1 Accent 3" w:semiHidden="0" w:uiPriority="63" w:unhideWhenUsed="0"/><w:lsdException w:name="Medium Shading 2 Accent 3" w:semiHidden="0" w:uiPriority="64" w:unhideWhenUsed="0"/><w:lsdException w:name="Medium List 1 Accent 3" w:semiHidden="0" w:uiPriority="65" w:unhideWhenUsed="0"/><w:lsdException w:name="Medium List 2 Accent 3" w:semiHidden="0" w:uiPriority="66" w:unhideWhenUsed="0"/><w:lsdException w:name="Medium Grid 1 Accent 3" w:semiHidden="0" w:uiPriority="67" w:unhideWhenUsed="0"/><w:lsdException w:name="Medium Grid 2 Accent 3" w:semiHidden="0" w:uiPriority="68" w:unhideWhenUsed="0"/><w:lsdException w:name="Medium Grid 3 Accent 3" w:semiHidden="0" w:uiPriority="69" w:unhideWhenUsed="0"/><w:lsdException w:name="Dark List Accent 3" w:semiHidden="0" w:uiPriority="70" w:unhideWhenUsed="0"/><w:lsdException w:name="Colorful Shading Accent 3" w:semiHidden="0" w:uiPriority="71" w:unhideWhenUsed="0"/><w:lsdException w:name="Colorful List Accent 3" w:semiHidden="0" w:uiPriority="72" w:unhideWhenUsed="0"/><w:lsdException w:name="Colorful Grid Accent 3" w:semiHidden="0" w:uiPriority="73" w:unhideWhenUsed="0"/><w:lsdException w:name="Light Shading Accent 4" w:semiHidden="0" w:uiPriority="60" w:unhideWhenUsed="0"/><w:lsdException w:name="Light List Accent 4" w:semiHidden="0" w:uiPriority="61" w:unhideWhenUsed="0"/><w:lsdException w:name="Light Grid Accent 4" w:semiHidden="0" w:uiPriority="62" w:unhideWhenUsed="0"/><w:lsdException w:name="Medium Shading 1 Accent 4" w:semiHidden="0" w:uiPriority="63" w:unhideWhenUsed="0"/><w:lsdException w:name="Medium Shading 2 Accent 4" w:semiHidden="0" w:uiPriority="64" w:unhideWhenUsed="0"/><w:lsdException w:name="Medium List 1 Accent 4" w:semiHidden="0" w:uiPriority="65" w:unhideWhenUsed="0"/><w:lsdException w:name="Medium List 2 Accent 4" w:semiHidden="0" w:uiPriority="66" w:unhideWhenUsed="0"/><w:lsdException w:name="Medium Grid 1 Accent 4" w:semiHidden="0" w:uiPriority="67" w:unhideWhenUsed="0"/><w:lsdException w:name="Medium Grid 2 Accent 4" w:semiHidden="0" w:uiPriority="68" w:unhideWhenUsed="0"/><w:lsdException w:name="Medium Grid 3 Accent 4" w:semiHidden="0" w:uiPriority="69" w:unhideWhenUsed="0"/><w:lsdException w:name="Dark List Accent 4" w:semiHidden="0" w:uiPriority="70" w:unhideWhenUsed="0"/><w:lsdException w:name="Colorful Shading Accent 4" w:semiHidden="0" w:uiPriority="71" w:unhideWhenUsed="0"/><w:lsdException w:name="Colorful List Accent 4" w:semiHidden="0" w:uiPriority="72" w:unhideWhenUsed="0"/><w:lsdException w:name="Colorful Grid Accent 4" w:semiHidden="0" w:uiPriority="73" w:unhideWhenUsed="0"/><w:lsdException w:name="Light Shading Accent 5" w:semiHidden="0" w:uiPriority="60" w:unhideWhenUsed="0"/><w:lsdException w:name="Light List Accent 5" w:semiHidden="0" w:uiPriority="61" w:unhideWhenUsed="0"/><w:lsdException w:name="Light Grid Accent 5" w:semiHidden="0" w:uiPriority="62" w:unhideWhenUsed="0"/><w:lsdException w:name="Medium Shading 1 Accent 5" w:semiHidden="0" w:uiPriority="63" w:unhideWhenUsed="0"/><w:lsdException w:name="Medium Shading 2 Accent 5" w:semiHidden="0" w:uiPriority="64" w:unhideWhenUsed="0"/><w:lsdException w:name="Medium List 1 Accent 5" w:semiHidden="0" w:uiPriority="65" w:unhideWhenUsed="0"/><w:lsdException w:name="Medium List 2 Accent 5" w:semiHidden="0" w:uiPriority="66" w:unhideWhenUsed="0"/><w:lsdException w:name="Medium Grid 1 Accent 5" w:semiHidden="0" w:uiPriority="67" w:unhideWhenUsed="0"/><w:lsdException w:name="Medium Grid 2 Accent 5" w:semiHidden="0" w:uiPriority="68" w:unhideWhenUsed="0"/><w:lsdException w:name="Medium Grid 3 Accent 5" w:semiHidden="0" w:uiPriority="69" w:unhideWhenUsed="0"/><w:lsdException w:name="Dark List Accent 5" w:semiHidden="0" w:uiPriority="70" w:unhideWhenUsed="0"/><w:lsdException w:name="Colorful Shading Accent 5" w:semiHidden="0" w:uiPriority="71" w:unhideWhenUsed="0"/><w:lsdException w:name="Colorful List Accent 5" w:semiHidden="0" w:uiPriority="72" w:unhideWhenUsed="0"/><w:lsdException w:name="Colorful Grid Accent 5" w:semiHidden="0" w:uiPriority="73" w:unhideWhenUsed="0"/><w:lsdException w:name="Light Shading Accent 6" w:semiHidden="0" w:uiPriority="60" w:unhideWhenUsed="0"/><w:lsdException w:name="Light List Accent 6" w:semiHidden="0" w:uiPriority="61" w:unhideWhenUsed="0"/><w:lsdException w:name="Light Grid Accent 6" w:semiHidden="0" w:uiPriority="62" w:unhideWhenUsed="0"/><w:lsdException w:name="Medium Shading 1 Accent 6" w:semiHidden="0" w:uiPriority="63" w:unhideWhenUsed="0"/><w:lsdException w:name="Medium Shading 2 Accent 6" w:semiHidden="0" w:uiPriority="64" w:unhideWhenUsed="0"/><w:lsdException w:name="Medium List 1 Accent 6" w:semiHidden="0" w:uiPriority="65" w:unhideWhenUsed="0"/><w:lsdException w:name="Medium List 2 Accent 6" w:semiHidden="0" w:uiPriority="66" w:unhideWhenUsed="0"/><w:lsdException w:name="Medium Grid 1 Accent 6" w:semiHidden="0" w:uiPriority="67" w:unhideWhenUsed="0"/><w:lsdException w:name="Medium Grid 2 Accent 6" w:semiHidden="0" w:uiPriority="68" w:unhideWhenUsed="0"/><w:lsdException w:name="Medium Grid 3 Accent 6" w:semiHidden="0" w:uiPriority="69" w:unhideWhenUsed="0"/><w:lsdException w:name="Dark List Accent 6" w:semiHidden="0" w:uiPriority="70" w:unhideWhenUsed="0"/><w:lsdException w:name="Colorful Shading Accent 6" w:semiHidden="0" w:uiPriority="71" w:unhideWhenUsed="0"/><w:lsdException w:name="Colorful List Accent 6" w:semiHidden="0" w:uiPriority="72" w:unhideWhenUsed="0"/><w:lsdException w:name="Colorful Grid Accent 6" w:semiHidden="0" w:uiPriority="73" w:unhideWhenUsed="0"/><w:lsdException w:name="Subtle Emphasis" w:semiHidden="0" w:uiPriority="19" w:unhideWhenUsed="0" w:qFormat="1"/><w:lsdException w:name="Intense Emphasis" w:semiHidden="0" w:uiPriority="21" w:unhideWhenUsed="0" w:qFormat="1"/><w:lsdException w:name="Subtle Reference" w:semiHidden="0" w:uiPriority="31" w:unhideWhenUsed="0" w:qFormat="1"/><w:lsdException w:name="Intense Reference" w:semiHidden="0" w:uiPriority="32" w:unhideWhenUsed="0" w:qFormat="1"/><w:lsdException w:name="Book Title" w:semiHidden="0" w:uiPriority="33" w:unhideWhenUsed="0" w:qFormat="1"/><w:lsdException w:name="Bibliography" w:uiPriority="37"/><w:lsdException w:name="TOC Heading" w:uiPriority="39"/></w:latentStyles><w:style w:type="paragraph" w:default="1" w:styleId="a5"><w:name w:val="Normal"/><w:qFormat/><w:rsid w:val="000719A8"/><w:pPr><w:widowControl w:val="0"/><w:jc w:val="both"/></w:pPr><w:rPr><w:rFonts w:ascii="Arial" w:eastAsia="楷体" w:hAnsi="Arial"/></w:rPr></w:style><w:style w:type="paragraph" w:styleId="1"><w:name w:val="heading 1"/><w:basedOn w:val="a5"/><w:next w:val="a5"/><w:link w:val="1Char"/><w:uiPriority w:val="9"/><w:qFormat/><w:rsid w:val="009E3B6F"/><w:pPr><w:keepNext/><w:keepLines/><w:spacing w:before="340" w:after="330" w:line="578" w:lineRule="auto"/><w:outlineLvl w:val="0"/></w:pPr><w:rPr><w:b/><w:bCs/><w:kern w:val="44"/><w:sz w:val="44"/><w:szCs w:val="44"/></w:rPr></w:style><w:style w:type="paragraph" w:styleId="21"><w:name w:val="heading 2"/><w:basedOn w:val="a5"/><w:next w:val="a5"/><w:link w:val="2Char"/><w:uiPriority w:val="9"/><w:semiHidden/><w:unhideWhenUsed/><w:qFormat/><w:rsid w:val="005F4F81"/><w:pPr><w:keepNext/><w:keepLines/><w:spacing w:before="260" w:after="260" w:line="416" w:lineRule="auto"/><w:outlineLvl w:val="1"/></w:pPr><w:rPr><w:rFonts w:asciiTheme="majorHAnsi" w:eastAsiaTheme="majorEastAsia" w:hAnsiTheme="majorHAnsi" w:cstheme="majorBidi"/><w:b/><w:bCs/><w:sz w:val="32"/><w:szCs w:val="32"/></w:rPr></w:style><w:style w:type="paragraph" w:styleId="31"><w:name w:val="heading 3"/><w:basedOn w:val="a5"/><w:next w:val="a5"/><w:link w:val="3Char"/><w:uiPriority w:val="9"/><w:semiHidden/><w:unhideWhenUsed/><w:qFormat/><w:rsid w:val="005F4F81"/><w:pPr><w:keepNext/><w:keepLines/><w:spacing w:before="260" w:after="260" w:line="416" w:lineRule="auto"/><w:outlineLvl w:val="2"/></w:pPr><w:rPr><w:b/><w:bCs/><w:sz w:val="32"/><w:szCs w:val="32"/></w:rPr></w:style><w:style w:type="paragraph" w:styleId="41"><w:name w:val="heading 4"/><w:basedOn w:val="a5"/><w:next w:val="a5"/><w:link w:val="4Char"/><w:uiPriority w:val="9"/><w:semiHidden/><w:unhideWhenUsed/><w:qFormat/><w:rsid w:val="005F4F81"/><w:pPr><w:keepNext/><w:keepLines/><w:spacing w:before="280" w:after="290" w:line="376" w:lineRule="auto"/><w:outlineLvl w:val="3"/></w:pPr><w:rPr><w:rFonts w:asciiTheme="majorHAnsi" w:eastAsiaTheme="majorEastAsia" w:hAnsiTheme="majorHAnsi" w:cstheme="majorBidi"/><w:b/><w:bCs/><w:sz w:val="28"/><w:szCs w:val="28"/></w:rPr></w:style><w:style w:type="paragraph" w:styleId="51"><w:name w:val="heading 5"/><w:basedOn w:val="a5"/><w:next w:val="a5"/><w:link w:val="5Char"/><w:uiPriority w:val="9"/><w:semiHidden/><w:unhideWhenUsed/><w:qFormat/><w:rsid w:val="005F4F81"/><w:pPr><w:keepNext/><w:keepLines/><w:spacing w:before="280" w:after="290" w:line="376" w:lineRule="auto"/><w:outlineLvl w:val="4"/></w:pPr><w:rPr><w:b/><w:bCs/><w:sz w:val="28"/><w:szCs w:val="28"/></w:rPr></w:style><w:style w:type="paragraph" w:styleId="6"><w:name w:val="heading 6"/><w:basedOn w:val="a5"/><w:next w:val="a5"/><w:link w:val="6Char"/><w:uiPriority w:val="9"/><w:semiHidden/><w:unhideWhenUsed/><w:qFormat/><w:rsid w:val="005F4F81"/><w:pPr><w:keepNext/><w:keepLines/><w:spacing w:before="240" w:after="64" w:line="320" w:lineRule="auto"/><w:outlineLvl w:val="5"/></w:pPr><w:rPr><w:rFonts w:asciiTheme="majorHAnsi" w:eastAsiaTheme="majorEastAsia" w:hAnsiTheme="majorHAnsi" w:cstheme="majorBidi"/><w:b/><w:bCs/><w:sz w:val="24"/><w:szCs w:val="24"/></w:rPr></w:style><w:style w:type="paragraph" w:styleId="7"><w:name w:val="heading 7"/><w:basedOn w:val="a5"/><w:next w:val="a5"/><w:link w:val="7Char"/><w:uiPriority w:val="9"/><w:semiHidden/><w:unhideWhenUsed/><w:qFormat/><w:rsid w:val="005F4F81"/><w:pPr><w:keepNext/><w:keepLines/><w:spacing w:before="240" w:after="64" w:line="320" w:lineRule="auto"/><w:outlineLvl w:val="6"/></w:pPr><w:rPr><w:b/><w:bCs/><w:sz w:val="24"/><w:szCs w:val="24"/></w:rPr></w:style><w:style w:type="paragraph" w:styleId="8"><w:name w:val="heading 8"/><w:basedOn w:val="a5"/><w:next w:val="a5"/><w:link w:val="8Char"/><w:uiPriority w:val="9"/><w:semiHidden/><w:unhideWhenUsed/><w:qFormat/><w:rsid w:val="005F4F81"/><w:pPr><w:keepNext/><w:keepLines/><w:spacing w:before="240" w:after="64" w:line="320" w:lineRule="auto"/><w:outlineLvl w:val="7"/></w:pPr><w:rPr><w:rFonts w:asciiTheme="majorHAnsi" w:eastAsiaTheme="majorEastAsia" w:hAnsiTheme="majorHAnsi" w:cstheme="majorBidi"/><w:sz w:val="24"/><w:szCs w:val="24"/></w:rPr></w:style><w:style w:type="paragraph" w:styleId="9"><w:name w:val="heading 9"/><w:basedOn w:val="a5"/><w:next w:val="a5"/><w:link w:val="9Char"/><w:uiPriority w:val="9"/><w:semiHidden/><w:unhideWhenUsed/><w:qFormat/><w:rsid w:val="005F4F81"/><w:pPr><w:keepNext/><w:keepLines/><w:spacing w:before="240" w:after="64" w:line="320" w:lineRule="auto"/><w:outlineLvl w:val="8"/></w:pPr><w:rPr><w:rFonts w:asciiTheme="majorHAnsi" w:eastAsiaTheme="majorEastAsia" w:hAnsiTheme="majorHAnsi" w:cstheme="majorBidi"/><w:szCs w:val="21"/></w:rPr></w:style><w:style w:type="character" w:default="1" w:styleId="a6"><w:name w:val="Default Paragraph Font"/><w:uiPriority w:val="1"/><w:semiHidden/><w:unhideWhenUsed/></w:style><w:style w:type="table" w:default="1" w:styleId="a7"><w:name w:val="Normal Table"/><w:uiPriority w:val="99"/><w:semiHidden/><w:unhideWhenUsed/><w:tblPr><w:tblInd w:w="0" w:type="dxa"/><w:tblCellMar><w:top w:w="0" w:type="dxa"/><w:left w:w="108" w:type="dxa"/><w:bottom w:w="0" w:type="dxa"/><w:right w:w="108" w:type="dxa"/></w:tblCellMar></w:tblPr></w:style><w:style w:type="numbering" w:default="1" w:styleId="a8"><w:name w:val="No List"/><w:uiPriority w:val="99"/><w:semiHidden/><w:unhideWhenUsed/></w:style><w:style w:type="paragraph" w:styleId="a9"><w:name w:val="header"/><w:basedOn w:val="a5"/><w:link w:val="Char"/><w:uiPriority w:val="99"/><w:unhideWhenUsed/><w:rsid w:val="004964FE"/><w:pPr><w:pBdr><w:bottom w:val="single" w:sz="6" w:space="1" w:color="auto"/></w:pBdr><w:tabs><w:tab w:val="center" w:pos="4153"/><w:tab w:val="right" w:pos="8306"/></w:tabs><w:snapToGrid w:val="0"/><w:jc w:val="center"/></w:pPr><w:rPr><w:sz w:val="18"/><w:szCs w:val="18"/></w:rPr></w:style><w:style w:type="character" w:customStyle="1" w:styleId="Char"><w:name w:val="页眉 Char"/><w:basedOn w:val="a6"/><w:link w:val="a9"/><w:uiPriority w:val="99"/><w:rsid w:val="004964FE"/><w:rPr><w:sz w:val="18"/><w:szCs w:val="18"/></w:rPr></w:style><w:style w:type="paragraph" w:styleId="aa"><w:name w:val="footer"/><w:basedOn w:val="a5"/><w:link w:val="Char0"/><w:uiPriority w:val="99"/><w:unhideWhenUsed/><w:rsid w:val="004964FE"/><w:pPr><w:tabs><w:tab w:val="center" w:pos="4153"/><w:tab w:val="right" w:pos="8306"/></w:tabs><w:snapToGrid w:val="0"/><w:jc w:val="left"/></w:pPr><w:rPr><w:sz w:val="18"/><w:szCs w:val="18"/></w:rPr></w:style><w:style w:type="character" w:customStyle="1" w:styleId="Char0"><w:name w:val="页脚 Char"/><w:basedOn w:val="a6"/><w:link w:val="aa"/><w:uiPriority w:val="99"/><w:rsid w:val="004964FE"/><w:rPr><w:sz w:val="18"/><w:szCs w:val="18"/></w:rPr></w:style><w:style w:type="table" w:styleId="ab"><w:name w:val="Table Grid"/><w:basedOn w:val="a7"/><w:uiPriority w:val="39"/><w:rsid w:val="0083114D"/><w:tblPr><w:tblBorders><w:top w:val="single" w:sz="4" w:space="0" w:color="auto"/><w:left w:val="single" w:sz="4" w:space="0" w:color="auto"/><w:bottom w:val="single" w:sz="4" w:space="0" w:color="auto"/><w:right w:val="single" w:sz="4" w:space="0" w:color="auto"/><w:insideH w:val="single" w:sz="4" w:space="0" w:color="auto"/><w:insideV w:val="single" w:sz="4" w:space="0" w:color="auto"/></w:tblBorders></w:tblPr></w:style><w:style w:type="paragraph" w:customStyle="1" w:styleId="a3"><w:name w:val="要点目录"/><w:basedOn w:val="a5"/><w:qFormat/><w:rsid w:val="00B549F5"/><w:pPr><w:numPr><w:numId w:val="1"/></w:numPr><w:autoSpaceDE w:val="0"/><w:autoSpaceDN w:val="0"/><w:adjustRightInd w:val="0"/><w:ind w:rightChars="100" w:right="100"/><w:jc w:val="left"/></w:pPr><w:rPr><w:rFonts w:ascii="Wingdings" w:hAnsi="Wingdings" w:cs="Wingdings"/><w:b/><w:kern w:val="0"/><w:szCs w:val="21"/></w:rPr></w:style><w:style w:type="paragraph" w:customStyle="1" w:styleId="ac"><w:name w:val="核心观点标题"/><w:basedOn w:val="a3"/><w:link w:val="Char1"/><w:qFormat/><w:rsid w:val="00DB0F6D"/><w:pPr><w:framePr w:hSpace="180" w:wrap="around" w:vAnchor="page" w:hAnchor="page" w:x="16" w:y="211"/><w:adjustRightInd/><w:spacing w:line="288" w:lineRule="auto"/><w:ind w:left="0" w:rightChars="0" w:right="0" w:firstLine="0"/></w:pPr><w:rPr><w:rFonts w:ascii="Arial" w:hAnsi="Arial"/></w:rPr></w:style><w:style w:type="paragraph" w:customStyle="1" w:styleId="ad"><w:name w:val="核心观点内容"/><w:basedOn w:val="a5"/><w:link w:val="Char2"/><w:qFormat/><w:rsid w:val="003D4740"/><w:pPr><w:framePr w:hSpace="180" w:wrap="around" w:vAnchor="page" w:hAnchor="page" w:x="16" w:y="211"/><w:autoSpaceDE w:val="0"/><w:autoSpaceDN w:val="0"/><w:adjustRightInd w:val="0"/><w:spacing w:line="336" w:lineRule="auto"/><w:jc w:val="left"/></w:pPr><w:rPr><w:rFonts w:cs="楷体_GB2312"/><w:kern w:val="0"/><w:szCs w:val="21"/></w:rPr></w:style><w:style w:type="character" w:customStyle="1" w:styleId="Char1"><w:name w:val="核心观点标题 Char"/><w:basedOn w:val="a6"/><w:link w:val="ac"/><w:rsid w:val="00DB0F6D"/><w:rPr><w:rFonts w:ascii="Arial" w:eastAsia="楷体" w:hAnsi="Arial" w:cs="Wingdings"/><w:b/><w:kern w:val="0"/><w:szCs w:val="21"/></w:rPr></w:style><w:style w:type="character" w:customStyle="1" w:styleId="Char2"><w:name w:val="核心观点内容 Char"/><w:basedOn w:val="a6"/><w:link w:val="ad"/><w:rsid w:val="003D4740"/><w:rPr><w:rFonts w:ascii="Arial" w:eastAsia="楷体" w:hAnsi="Arial" w:cs="楷体_GB2312"/><w:kern w:val="0"/><w:szCs w:val="21"/></w:rPr></w:style><w:style w:type="paragraph" w:customStyle="1" w:styleId="ae"><w:name w:val="基本数据数值"/><w:basedOn w:val="a5"/><w:link w:val="Char3"/><w:qFormat/><w:rsid w:val="000719A8"/><w:pPr><w:framePr w:hSpace="180" w:wrap="around" w:vAnchor="page" w:hAnchor="page" w:x="16" w:y="211"/><w:jc w:val="right"/></w:pPr><w:rPr><w:rFonts w:ascii="楷体_GB2312" w:hAnsiTheme="minorHAnsi"/><w:sz w:val="18"/><w:szCs w:val="18"/></w:rPr></w:style><w:style w:type="character" w:customStyle="1" w:styleId="Char3"><w:name w:val="基本数据数值 Char"/><w:basedOn w:val="a6"/><w:link w:val="ae"/><w:rsid w:val="000719A8"/><w:rPr><w:rFonts w:ascii="楷体_GB2312" w:eastAsia="楷体"/><w:sz w:val="18"/><w:szCs w:val="18"/></w:rPr></w:style><w:style w:type="paragraph" w:customStyle="1" w:styleId="af"><w:name w:val="相关报告列表"/><w:basedOn w:val="ae"/><w:link w:val="Char4"/><w:qFormat/><w:rsid w:val="00756436"/><w:pPr><w:framePr w:wrap="around"/><w:jc w:val="left"/></w:pPr></w:style><w:style w:type="character" w:customStyle="1" w:styleId="Char4"><w:name w:val="相关报告列表 Char"/><w:basedOn w:val="Char3"/><w:link w:val="af"/><w:rsid w:val="00756436"/><w:rPr><w:rFonts w:ascii="楷体_GB2312" w:eastAsia="楷体_GB2312"/><w:sz w:val="18"/><w:szCs w:val="18"/></w:rPr></w:style><w:style w:type="paragraph" w:styleId="af0"><w:name w:val="List Paragraph"/><w:basedOn w:val="a5"/><w:uiPriority w:val="34"/><w:qFormat/><w:rsid w:val="00504E47"/><w:pPr><w:ind w:firstLineChars="200" w:firstLine="420"/></w:pPr></w:style><w:style w:type="paragraph" w:customStyle="1" w:styleId="af1"><w:name w:val="报告页眉"/><w:basedOn w:val="a9"/><w:link w:val="Char5"/><w:qFormat/><w:rsid w:val="000719A8"/><w:pPr><w:pBdr><w:bottom w:val="single" w:sz="8" w:space="4" w:color="FF7800"/></w:pBdr><w:jc w:val="left"/></w:pPr><w:rPr><w:color w:val="C1000E"/></w:rPr></w:style><w:style w:type="paragraph" w:customStyle="1" w:styleId="af2"><w:name w:val="报告页脚"/><w:basedOn w:val="aa"/><w:link w:val="Char6"/><w:qFormat/><w:rsid w:val="000719A8"/><w:pPr><w:pBdr><w:top w:val="single" w:sz="8" w:space="1" w:color="FF7800"/></w:pBdr><w:jc w:val="center"/></w:pPr></w:style><w:style w:type="character" w:customStyle="1" w:styleId="Char5"><w:name w:val="报告页眉 Char"/><w:basedOn w:val="Char"/><w:link w:val="af1"/><w:rsid w:val="000719A8"/><w:rPr><w:rFonts w:ascii="Arial" w:eastAsia="楷体" w:hAnsi="Arial"/><w:color w:val="C1000E"/><w:sz w:val="18"/><w:szCs w:val="18"/></w:rPr></w:style><w:style w:type="character" w:customStyle="1" w:styleId="Char6"><w:name w:val="报告页脚 Char"/><w:basedOn w:val="Char0"/><w:link w:val="af2"/><w:rsid w:val="000719A8"/><w:rPr><w:rFonts w:ascii="Arial" w:eastAsia="楷体" w:hAnsi="Arial"/><w:sz w:val="18"/><w:szCs w:val="18"/></w:rPr></w:style><w:style w:type="paragraph" w:styleId="af3"><w:name w:val="Balloon Text"/><w:basedOn w:val="a5"/><w:link w:val="Char7"/><w:uiPriority w:val="99"/><w:semiHidden/><w:unhideWhenUsed/><w:rsid w:val="00460CE1"/><w:rPr><w:sz w:val="18"/><w:szCs w:val="18"/></w:rPr></w:style><w:style w:type="character" w:customStyle="1" w:styleId="Char7"><w:name w:val="批注框文本 Char"/><w:basedOn w:val="a6"/><w:link w:val="af3"/><w:uiPriority w:val="99"/><w:semiHidden/><w:rsid w:val="00460CE1"/><w:rPr><w:rFonts w:ascii="Arial" w:eastAsia="楷体_GB2312" w:hAnsi="Arial"/><w:sz w:val="18"/><w:szCs w:val="18"/></w:rPr></w:style><w:style w:type="paragraph" w:customStyle="1" w:styleId="af4"><w:name w:val="主标题股票名称"/><w:basedOn w:val="a5"/><w:link w:val="Char8"/><w:qFormat/><w:rsid w:val="00596083"/><w:pPr><w:framePr w:wrap="around" w:hAnchor="margin" w:xAlign="center" w:yAlign="center"/><w:tabs><w:tab w:val="left" w:pos="1019"/></w:tabs></w:pPr><w:rPr><w:rFonts w:ascii="楷体_GB2312"/><w:b/><w:kern w:val="0"/><w:sz w:val="36"/><w:szCs w:val="36"/></w:rPr></w:style><w:style w:type="paragraph" w:customStyle="1" w:styleId="af5"><w:name w:val="主标题股票代码"/><w:basedOn w:val="a5"/><w:link w:val="Char9"/><w:qFormat/><w:rsid w:val="00596083"/><w:pPr><w:framePr w:wrap="around" w:hAnchor="margin" w:xAlign="center" w:yAlign="center"/><w:tabs><w:tab w:val="left" w:pos="1019"/></w:tabs></w:pPr><w:rPr><w:rFonts w:cs="Arial"/><w:kern w:val="0"/><w:sz w:val="36"/><w:szCs w:val="36"/></w:rPr></w:style><w:style w:type="character" w:customStyle="1" w:styleId="Char8"><w:name w:val="主标题股票名称 Char"/><w:basedOn w:val="a6"/><w:link w:val="af4"/><w:rsid w:val="00596083"/><w:rPr><w:rFonts w:ascii="楷体_GB2312" w:eastAsia="楷体_GB2312" w:hAnsi="Arial"/><w:b/><w:kern w:val="0"/><w:sz w:val="36"/><w:szCs w:val="36"/></w:rPr></w:style><w:style w:type="paragraph" w:customStyle="1" w:styleId="af6"><w:name w:val="主标题行业名称"/><w:basedOn w:val="a5"/><w:link w:val="Chara"/><w:qFormat/><w:rsid w:val="00992562"/><w:pPr><w:framePr w:wrap="around" w:hAnchor="margin" w:xAlign="center" w:yAlign="center"/><w:tabs><w:tab w:val="left" w:pos="1019"/></w:tabs></w:pPr><w:rPr><w:rFonts w:ascii="楷体_GB2312"/><w:kern w:val="0"/><w:sz w:val="28"/><w:szCs w:val="28"/></w:rPr></w:style><w:style w:type="character" w:customStyle="1" w:styleId="Char9"><w:name w:val="主标题股票代码 Char"/><w:basedOn w:val="a6"/><w:link w:val="af5"/><w:rsid w:val="00596083"/><w:rPr><w:rFonts w:ascii="Arial" w:eastAsia="楷体_GB2312" w:hAnsi="Arial" w:cs="Arial"/><w:kern w:val="0"/><w:sz w:val="36"/><w:szCs w:val="36"/></w:rPr></w:style><w:style w:type="paragraph" w:customStyle="1" w:styleId="af7"><w:name w:val="报告副标题"/><w:basedOn w:val="a5"/><w:link w:val="Charb"/><w:qFormat/><w:rsid w:val="000719A8"/><w:pPr><w:framePr w:wrap="around" w:hAnchor="margin" w:xAlign="center" w:yAlign="center"/><w:tabs><w:tab w:val="left" w:pos="1019"/></w:tabs><w:ind w:firstLineChars="150" w:firstLine="452"/></w:pPr><w:rPr><w:rFonts w:ascii="楷体_GB2312"/><w:b/><w:kern w:val="0"/><w:sz w:val="30"/><w:szCs w:val="30"/></w:rPr></w:style><w:style w:type="character" w:customStyle="1" w:styleId="Chara"><w:name w:val="主标题行业名称 Char"/><w:basedOn w:val="a6"/><w:link w:val="af6"/><w:rsid w:val="00992562"/><w:rPr><w:rFonts w:ascii="楷体_GB2312" w:eastAsia="楷体_GB2312" w:hAnsi="Arial"/><w:kern w:val="0"/><w:sz w:val="28"/><w:szCs w:val="28"/></w:rPr></w:style><w:style w:type="paragraph" w:customStyle="1" w:styleId="af8"><w:name w:val="报告日期"/><w:basedOn w:val="a5"/><w:link w:val="Charc"/><w:qFormat/><w:rsid w:val="000719A8"/><w:pPr><w:framePr w:wrap="around" w:hAnchor="margin" w:xAlign="center" w:yAlign="center"/><w:tabs><w:tab w:val="left" w:pos="1019"/></w:tabs><w:jc w:val="right"/></w:pPr><w:rPr><w:kern w:val="0"/></w:rPr></w:style><w:style w:type="character" w:customStyle="1" w:styleId="Charb"><w:name w:val="报告副标题 Char"/><w:basedOn w:val="a6"/><w:link w:val="af7"/><w:rsid w:val="000719A8"/><w:rPr><w:rFonts w:ascii="楷体_GB2312" w:eastAsia="楷体" w:hAnsi="Arial"/><w:b/><w:kern w:val="0"/><w:sz w:val="30"/><w:szCs w:val="30"/></w:rPr></w:style><w:style w:type="paragraph" w:customStyle="1" w:styleId="af9"><w:name w:val="报告类型"/><w:basedOn w:val="a5"/><w:link w:val="Chard"/><w:rsid w:val="00DC3A6B"/><w:pPr><w:framePr w:wrap="around" w:hAnchor="margin" w:xAlign="center" w:yAlign="center"/><w:spacing w:line="400" w:lineRule="exact"/><w:ind w:left="113" w:right="113"/><w:jc w:val="right"/></w:pPr><w:rPr><w:rFonts w:ascii="楷体_GB2312" w:hAnsiTheme="minorHAnsi"/><w:b/><w:color w:val="4C4947"/><w:sz w:val="24"/><w:szCs w:val="24"/></w:rPr></w:style><w:style w:type="character" w:customStyle="1" w:styleId="Charc"><w:name w:val="报告日期 Char"/><w:basedOn w:val="a6"/><w:link w:val="af8"/><w:rsid w:val="000719A8"/><w:rPr><w:rFonts w:ascii="Arial" w:eastAsia="楷体" w:hAnsi="Arial"/><w:kern w:val="0"/></w:rPr></w:style><w:style w:type="paragraph" w:customStyle="1" w:styleId="a1"><w:name w:val="国联证券报告正文一级标题"/><w:basedOn w:val="a5"/><w:link w:val="Chare"/><w:qFormat/><w:rsid w:val="00C11D3B"/><w:pPr><w:numPr><w:numId w:val="18"/></w:numPr><w:spacing w:beforeLines="50"/><w:jc w:val="left"/><w:outlineLvl w:val="0"/></w:pPr><w:rPr><w:b/><w:sz w:val="28"/></w:rPr></w:style><w:style w:type="character" w:customStyle="1" w:styleId="Chard"><w:name w:val="报告类型 Char"/><w:basedOn w:val="a6"/><w:link w:val="af9"/><w:rsid w:val="00DC3A6B"/><w:rPr><w:rFonts w:ascii="楷体_GB2312" w:eastAsia="楷体_GB2312"/><w:b/><w:color w:val="4C4947"/><w:sz w:val="24"/><w:szCs w:val="24"/></w:rPr></w:style><w:style w:type="character" w:customStyle="1" w:styleId="Chare"><w:name w:val="国联证券报告正文一级标题 Char"/><w:basedOn w:val="a6"/><w:link w:val="a1"/><w:rsid w:val="00C11D3B"/><w:rPr><w:rFonts w:ascii="Arial" w:eastAsia="楷体" w:hAnsi="Arial"/><w:b/><w:sz w:val="28"/></w:rPr></w:style><w:style w:type="paragraph" w:customStyle="1" w:styleId="a2"><w:name w:val="国联证券报告正文二级标题"/><w:basedOn w:val="a5"/><w:link w:val="Charf"/><w:qFormat/><w:rsid w:val="00C11D3B"/><w:pPr><w:numPr><w:ilvl w:val="1"/><w:numId w:val="18"/></w:numPr><w:tabs><w:tab w:val="right" w:leader="dot" w:pos="12424"/></w:tabs><w:spacing w:beforeLines="50" w:after="100" w:afterAutospacing="1"/><w:ind w:left="2972"/><w:jc w:val="left"/><w:outlineLvl w:val="1"/></w:pPr><w:rPr><w:rFonts w:cs="Times New Roman"/><w:b/><w:bCs/><w:sz w:val="24"/><w:szCs w:val="32"/></w:rPr></w:style><w:style w:type="character" w:customStyle="1" w:styleId="Charf"><w:name w:val="国联证券报告正文二级标题 Char"/><w:link w:val="a2"/><w:rsid w:val="00C11D3B"/><w:rPr><w:rFonts w:ascii="Arial" w:eastAsia="楷体" w:hAnsi="Arial" w:cs="Times New Roman"/><w:b/><w:bCs/><w:sz w:val="24"/><w:szCs w:val="32"/></w:rPr></w:style><w:style w:type="paragraph" w:customStyle="1" w:styleId="a4"><w:name w:val="国联证券报告正文三级标题"/><w:basedOn w:val="a5"/><w:link w:val="Charf0"/><w:qFormat/><w:rsid w:val="00874740"/><w:pPr><w:numPr><w:numId w:val="6"/></w:numPr><w:spacing w:beforeLines="50"/><w:ind w:leftChars="1200" w:left="1620"/></w:pPr></w:style><w:style w:type="paragraph" w:customStyle="1" w:styleId="afa"><w:name w:val="国联证券报告正文"/><w:basedOn w:val="a5"/><w:link w:val="Charf1"/><w:qFormat/><w:rsid w:val="000719A8"/><w:pPr><w:spacing w:beforeLines="50" w:afterLines="50" w:line="276" w:lineRule="auto"/><w:ind w:leftChars="1200" w:left="1200" w:firstLineChars="200" w:firstLine="200"/></w:pPr></w:style><w:style w:type="character" w:customStyle="1" w:styleId="Charf0"><w:name w:val="国联证券报告正文三级标题 Char"/><w:basedOn w:val="a6"/><w:link w:val="a4"/><w:rsid w:val="00874740"/><w:rPr><w:rFonts w:ascii="Arial" w:eastAsia="楷体_GB2312" w:hAnsi="Arial"/></w:rPr></w:style><w:style w:type="paragraph" w:customStyle="1" w:styleId="afb"><w:name w:val="图表来源"/><w:basedOn w:val="a5"/><w:link w:val="Charf2"/><w:qFormat/><w:rsid w:val="000719A8"/><w:pPr><w:jc w:val="left"/></w:pPr><w:rPr><w:sz w:val="15"/><w:szCs w:val="15"/></w:rPr></w:style><w:style w:type="character" w:customStyle="1" w:styleId="Charf1"><w:name w:val="国联证券报告正文 Char"/><w:basedOn w:val="a6"/><w:link w:val="afa"/><w:qFormat/><w:rsid w:val="000719A8"/><w:rPr><w:rFonts w:ascii="Arial" w:eastAsia="楷体" w:hAnsi="Arial"/></w:rPr></w:style><w:style w:type="paragraph" w:customStyle="1" w:styleId="afc"><w:name w:val="图表标题"/><w:basedOn w:val="afd"/><w:qFormat/><w:rsid w:val="003015CB"/><w:pPr><w:keepNext/><w:framePr w:hSpace="181" w:wrap="notBeside" w:vAnchor="text" w:hAnchor="text" w:y="1"/><w:widowControl/><w:suppressAutoHyphens/><w:kinsoku w:val="0"/><w:spacing w:after="40" w:line="240" w:lineRule="exact"/><w:ind w:leftChars="0" w:left="0" w:firstLineChars="0" w:firstLine="0"/><w:suppressOverlap/></w:pPr><w:rPr><w:rFonts w:cs="Arial"/><w:b/><w:bCs/><w:i/><w:noProof/><w:szCs w:val="24"/></w:rPr></w:style><w:style w:type="paragraph" w:styleId="afe"><w:name w:val="Body Text"/><w:basedOn w:val="a5"/><w:link w:val="Charf3"/><w:uiPriority w:val="99"/><w:semiHidden/><w:unhideWhenUsed/><w:rsid w:val="00F45E61"/><w:pPr><w:spacing w:after="120"/></w:pPr></w:style><w:style w:type="character" w:customStyle="1" w:styleId="Charf3"><w:name w:val="正文文本 Char"/><w:basedOn w:val="a6"/><w:link w:val="afe"/><w:uiPriority w:val="99"/><w:semiHidden/><w:rsid w:val="00F45E61"/><w:rPr><w:rFonts w:ascii="Arial" w:eastAsia="楷体_GB2312" w:hAnsi="Arial"/></w:rPr></w:style><w:style w:type="paragraph" w:styleId="afd"><w:name w:val="table of figures"/><w:basedOn w:val="a5"/><w:next w:val="a5"/><w:uiPriority w:val="99"/><w:unhideWhenUsed/><w:rsid w:val="00033BF3"/><w:pPr><w:ind w:leftChars="1000" w:left="1200" w:hangingChars="200" w:hanging="200"/></w:pPr></w:style><w:style w:type="character" w:styleId="aff"><w:name w:val="annotation reference"/><w:basedOn w:val="a6"/><w:uiPriority w:val="99"/><w:semiHidden/><w:unhideWhenUsed/><w:rsid w:val="00B90047"/><w:rPr><w:sz w:val="21"/><w:szCs w:val="21"/></w:rPr></w:style><w:style w:type="paragraph" w:styleId="aff0"><w:name w:val="annotation text"/><w:basedOn w:val="a5"/><w:link w:val="Charf4"/><w:uiPriority w:val="99"/><w:semiHidden/><w:unhideWhenUsed/><w:rsid w:val="00B90047"/><w:pPr><w:jc w:val="left"/></w:pPr></w:style><w:style w:type="character" w:customStyle="1" w:styleId="Charf4"><w:name w:val="批注文字 Char"/><w:basedOn w:val="a6"/><w:link w:val="aff0"/><w:uiPriority w:val="99"/><w:semiHidden/><w:rsid w:val="00B90047"/><w:rPr><w:rFonts w:ascii="Arial" w:eastAsia="楷体_GB2312" w:hAnsi="Arial"/></w:rPr></w:style><w:style w:type="paragraph" w:styleId="aff1"><w:name w:val="annotation subject"/><w:basedOn w:val="aff0"/><w:next w:val="aff0"/><w:link w:val="Charf5"/><w:uiPriority w:val="99"/><w:semiHidden/><w:unhideWhenUsed/><w:rsid w:val="00B90047"/><w:rPr><w:b/><w:bCs/></w:rPr></w:style><w:style w:type="character" w:customStyle="1" w:styleId="Charf5"><w:name w:val="批注主题 Char"/><w:basedOn w:val="Charf4"/><w:link w:val="aff1"/><w:uiPriority w:val="99"/><w:semiHidden/><w:rsid w:val="00B90047"/><w:rPr><w:rFonts w:ascii="Arial" w:eastAsia="楷体_GB2312" w:hAnsi="Arial"/><w:b/><w:bCs/></w:rPr></w:style><w:style w:type="paragraph" w:customStyle="1" w:styleId="FooterTitle"><w:name w:val="FooterTitle"/><w:basedOn w:val="afe"/><w:rsid w:val="00874740"/><w:pPr><w:framePr w:hSpace="180" w:wrap="around" w:vAnchor="text" w:hAnchor="text" w:y="1"/><w:tabs><w:tab w:val="right" w:pos="11743"/></w:tabs><w:spacing w:before="40" w:after="160"/><w:suppressOverlap/></w:pPr><w:rPr><w:rFonts w:cs="Times New Roman"/><w:color w:val="C00000"/><w:sz w:val="15"/><w:szCs w:val="24"/></w:rPr></w:style><w:style w:type="paragraph" w:customStyle="1" w:styleId="TableLargeTitle"><w:name w:val="TableLargeTitle"/><w:basedOn w:val="afd"/><w:rsid w:val="00874740"/><w:pPr><w:keepNext/><w:framePr w:hSpace="180" w:wrap="around" w:vAnchor="text" w:hAnchor="text" w:y="1"/><w:widowControl/><w:tabs><w:tab w:val="right" w:leader="dot" w:pos="8644"/><w:tab w:val="right" w:leader="dot" w:pos="10649"/></w:tabs><w:suppressAutoHyphens/><w:kinsoku w:val="0"/><w:spacing w:after="40" w:line="240" w:lineRule="exact"/><w:ind w:leftChars="0" w:left="0" w:firstLineChars="0" w:firstLine="0"/><w:suppressOverlap/></w:pPr><w:rPr><w:rFonts w:cs="Arial"/><w:b/><w:bCs/><w:i/><w:noProof/><w:color w:val="C00000"/><w:szCs w:val="24"/></w:rPr></w:style><w:style w:type="paragraph" w:customStyle="1" w:styleId="aff2"><w:name w:val="等宽图表标题"/><w:basedOn w:val="a5"/><w:link w:val="Charf6"/><w:qFormat/><w:rsid w:val="000719A8"/><w:rPr><w:rFonts w:ascii="楷体_GB2312"/><w:b/><w:i/></w:rPr></w:style><w:style w:type="character" w:customStyle="1" w:styleId="1Char"><w:name w:val="标题 1 Char"/><w:basedOn w:val="a6"/><w:link w:val="1"/><w:uiPriority w:val="9"/><w:rsid w:val="009E3B6F"/><w:rPr><w:rFonts w:ascii="Arial" w:eastAsia="楷体_GB2312" w:hAnsi="Arial"/><w:b/><w:bCs/><w:kern w:val="44"/><w:sz w:val="44"/><w:szCs w:val="44"/></w:rPr></w:style><w:style w:type="character" w:customStyle="1" w:styleId="Charf6"><w:name w:val="等宽图表标题 Char"/><w:basedOn w:val="a6"/><w:link w:val="aff2"/><w:rsid w:val="000719A8"/><w:rPr><w:rFonts w:ascii="楷体_GB2312" w:eastAsia="楷体" w:hAnsi="Arial"/><w:b/><w:i/></w:rPr></w:style><w:style w:type="paragraph" w:styleId="TOC"><w:name w:val="TOC Heading"/><w:basedOn w:val="10"/><w:next w:val="10"/><w:uiPriority w:val="39"/><w:unhideWhenUsed/><w:rsid w:val="007D1632"/><w:pPr><w:widowControl/><w:spacing w:before="240" w:line="259" w:lineRule="auto"/><w:ind w:left="1000"/><w:jc w:val="left"/></w:pPr><w:rPr><w:rFonts w:asciiTheme="majorHAnsi" w:hAnsiTheme="majorHAnsi" w:cstheme="majorBidi"/><w:bCs/><w:kern w:val="0"/><w:sz w:val="28"/><w:szCs w:val="32"/></w:rPr></w:style><w:style w:type="paragraph" w:styleId="10"><w:name w:val="toc 1"/><w:basedOn w:val="a5"/><w:next w:val="a5"/><w:autoRedefine/><w:uiPriority w:val="39"/><w:unhideWhenUsed/><w:rsid w:val="007D1632"/><w:pPr><w:tabs><w:tab w:val="right" w:leader="dot" w:pos="10194"/></w:tabs><w:ind w:leftChars="1000" w:left="2100"/></w:pPr><w:rPr><w:rFonts w:ascii="楷体_GB2312"/><w:b/><w:noProof/></w:rPr></w:style><w:style w:type="paragraph" w:styleId="22"><w:name w:val="toc 2"/><w:basedOn w:val="a5"/><w:next w:val="a5"/><w:autoRedefine/><w:uiPriority w:val="39"/><w:unhideWhenUsed/><w:rsid w:val="007D1632"/><w:pPr><w:ind w:leftChars="1200" w:left="1200"/></w:pPr></w:style><w:style w:type="character" w:styleId="aff3"><w:name w:val="Hyperlink"/><w:basedOn w:val="a6"/><w:uiPriority w:val="99"/><w:unhideWhenUsed/><w:rsid w:val="009E3B6F"/><w:rPr><w:color w:val="0563C1" w:themeColor="hyperlink"/><w:u w:val="single"/></w:rPr></w:style><w:style w:type="character" w:customStyle="1" w:styleId="Charf2"><w:name w:val="图表来源 Char"/><w:basedOn w:val="a6"/><w:link w:val="afb"/><w:rsid w:val="000719A8"/><w:rPr><w:rFonts w:ascii="Arial" w:eastAsia="楷体" w:hAnsi="Arial"/><w:sz w:val="15"/><w:szCs w:val="15"/></w:rPr></w:style><w:style w:type="paragraph" w:styleId="aff4"><w:name w:val="caption"/><w:basedOn w:val="a5"/><w:next w:val="a5"/><w:uiPriority w:val="35"/><w:unhideWhenUsed/><w:qFormat/><w:rsid w:val="00782B6C"/><w:rPr><w:rFonts w:asciiTheme="majorHAnsi" w:eastAsia="黑体" w:hAnsiTheme="majorHAnsi" w:cstheme="majorBidi"/><w:sz w:val="20"/><w:szCs w:val="20"/></w:rPr></w:style><w:style w:type="paragraph" w:styleId="HTML"><w:name w:val="HTML Address"/><w:basedOn w:val="a5"/><w:link w:val="HTMLChar"/><w:uiPriority w:val="99"/><w:semiHidden/><w:unhideWhenUsed/><w:rsid w:val="005F4F81"/><w:rPr><w:i/><w:iCs/></w:rPr></w:style><w:style w:type="character" w:customStyle="1" w:styleId="HTMLChar"><w:name w:val="HTML 地址 Char"/><w:basedOn w:val="a6"/><w:link w:val="HTML"/><w:uiPriority w:val="99"/><w:semiHidden/><w:rsid w:val="005F4F81"/><w:rPr><w:rFonts w:ascii="Arial" w:eastAsia="楷体_GB2312" w:hAnsi="Arial"/><w:i/><w:iCs/></w:rPr></w:style><w:style w:type="paragraph" w:styleId="HTML0"><w:name w:val="HTML Preformatted"/><w:basedOn w:val="a5"/><w:link w:val="HTMLChar0"/><w:uiPriority w:val="99"/><w:semiHidden/><w:unhideWhenUsed/><w:rsid w:val="005F4F81"/><w:rPr><w:rFonts w:ascii="Courier New" w:hAnsi="Courier New" w:cs="Courier New"/><w:sz w:val="20"/><w:szCs w:val="20"/></w:rPr></w:style><w:style w:type="character" w:customStyle="1" w:styleId="HTMLChar0"><w:name w:val="HTML 预设格式 Char"/><w:basedOn w:val="a6"/><w:link w:val="HTML0"/><w:uiPriority w:val="99"/><w:semiHidden/><w:rsid w:val="005F4F81"/><w:rPr><w:rFonts w:ascii="Courier New" w:eastAsia="楷体_GB2312" w:hAnsi="Courier New" w:cs="Courier New"/><w:sz w:val="20"/><w:szCs w:val="20"/></w:rPr></w:style><w:style w:type="paragraph" w:styleId="aff5"><w:name w:val="Title"/><w:basedOn w:val="a5"/><w:next w:val="a5"/><w:link w:val="Charf7"/><w:uiPriority w:val="10"/><w:qFormat/><w:rsid w:val="005F4F81"/><w:pPr><w:spacing w:before="240" w:after="60"/><w:jc w:val="center"/><w:outlineLvl w:val="0"/></w:pPr><w:rPr><w:rFonts w:asciiTheme="majorHAnsi" w:eastAsia="宋体" w:hAnsiTheme="majorHAnsi" w:cstheme="majorBidi"/><w:b/><w:bCs/><w:sz w:val="32"/><w:szCs w:val="32"/></w:rPr></w:style><w:style w:type="character" w:customStyle="1" w:styleId="Charf7"><w:name w:val="标题 Char"/><w:basedOn w:val="a6"/><w:link w:val="aff5"/><w:uiPriority w:val="10"/><w:rsid w:val="005F4F81"/><w:rPr><w:rFonts w:asciiTheme="majorHAnsi" w:eastAsia="宋体" w:hAnsiTheme="majorHAnsi" w:cstheme="majorBidi"/><w:b/><w:bCs/><w:sz w:val="32"/><w:szCs w:val="32"/></w:rPr></w:style><w:style w:type="character" w:customStyle="1" w:styleId="2Char"><w:name w:val="标题 2 Char"/><w:basedOn w:val="a6"/><w:link w:val="21"/><w:uiPriority w:val="9"/><w:semiHidden/><w:rsid w:val="005F4F81"/><w:rPr><w:rFonts w:asciiTheme="majorHAnsi" w:eastAsiaTheme="majorEastAsia" w:hAnsiTheme="majorHAnsi" w:cstheme="majorBidi"/><w:b/><w:bCs/><w:sz w:val="32"/><w:szCs w:val="32"/></w:rPr></w:style><w:style w:type="character" w:customStyle="1" w:styleId="3Char"><w:name w:val="标题 3 Char"/><w:basedOn w:val="a6"/><w:link w:val="31"/><w:uiPriority w:val="9"/><w:semiHidden/><w:rsid w:val="005F4F81"/><w:rPr><w:rFonts w:ascii="Arial" w:eastAsia="楷体_GB2312" w:hAnsi="Arial"/><w:b/><w:bCs/><w:sz w:val="32"/><w:szCs w:val="32"/></w:rPr></w:style><w:style w:type="character" w:customStyle="1" w:styleId="4Char"><w:name w:val="标题 4 Char"/><w:basedOn w:val="a6"/><w:link w:val="41"/><w:uiPriority w:val="9"/><w:semiHidden/><w:rsid w:val="005F4F81"/><w:rPr><w:rFonts w:asciiTheme="majorHAnsi" w:eastAsiaTheme="majorEastAsia" w:hAnsiTheme="majorHAnsi" w:cstheme="majorBidi"/><w:b/><w:bCs/><w:sz w:val="28"/><w:szCs w:val="28"/></w:rPr></w:style><w:style w:type="character" w:customStyle="1" w:styleId="5Char"><w:name w:val="标题 5 Char"/><w:basedOn w:val="a6"/><w:link w:val="51"/><w:uiPriority w:val="9"/><w:semiHidden/><w:rsid w:val="005F4F81"/><w:rPr><w:rFonts w:ascii="Arial" w:eastAsia="楷体_GB2312" w:hAnsi="Arial"/><w:b/><w:bCs/><w:sz w:val="28"/><w:szCs w:val="28"/></w:rPr></w:style><w:style w:type="character" w:customStyle="1" w:styleId="6Char"><w:name w:val="标题 6 Char"/><w:basedOn w:val="a6"/><w:link w:val="6"/><w:uiPriority w:val="9"/><w:semiHidden/><w:rsid w:val="005F4F81"/><w:rPr><w:rFonts w:asciiTheme="majorHAnsi" w:eastAsiaTheme="majorEastAsia" w:hAnsiTheme="majorHAnsi" w:cstheme="majorBidi"/><w:b/><w:bCs/><w:sz w:val="24"/><w:szCs w:val="24"/></w:rPr></w:style><w:style w:type="character" w:customStyle="1" w:styleId="7Char"><w:name w:val="标题 7 Char"/><w:basedOn w:val="a6"/><w:link w:val="7"/><w:uiPriority w:val="9"/><w:semiHidden/><w:rsid w:val="005F4F81"/><w:rPr><w:rFonts w:ascii="Arial" w:eastAsia="楷体_GB2312" w:hAnsi="Arial"/><w:b/><w:bCs/><w:sz w:val="24"/><w:szCs w:val="24"/></w:rPr></w:style><w:style w:type="character" w:customStyle="1" w:styleId="8Char"><w:name w:val="标题 8 Char"/><w:basedOn w:val="a6"/><w:link w:val="8"/><w:uiPriority w:val="9"/><w:semiHidden/><w:rsid w:val="005F4F81"/><w:rPr><w:rFonts w:asciiTheme="majorHAnsi" w:eastAsiaTheme="majorEastAsia" w:hAnsiTheme="majorHAnsi" w:cstheme="majorBidi"/><w:sz w:val="24"/><w:szCs w:val="24"/></w:rPr></w:style><w:style w:type="character" w:customStyle="1" w:styleId="9Char"><w:name w:val="标题 9 Char"/><w:basedOn w:val="a6"/><w:link w:val="9"/><w:uiPriority w:val="9"/><w:semiHidden/><w:rsid w:val="005F4F81"/><w:rPr><w:rFonts w:asciiTheme="majorHAnsi" w:eastAsiaTheme="majorEastAsia" w:hAnsiTheme="majorHAnsi" w:cstheme="majorBidi"/><w:szCs w:val="21"/></w:rPr></w:style><w:style w:type="paragraph" w:styleId="aff6"><w:name w:val="Salutation"/><w:basedOn w:val="a5"/><w:next w:val="a5"/><w:link w:val="Charf8"/><w:uiPriority w:val="99"/><w:semiHidden/><w:unhideWhenUsed/><w:rsid w:val="005F4F81"/></w:style><w:style w:type="character" w:customStyle="1" w:styleId="Charf8"><w:name w:val="称呼 Char"/><w:basedOn w:val="a6"/><w:link w:val="aff6"/><w:uiPriority w:val="99"/><w:semiHidden/><w:rsid w:val="005F4F81"/><w:rPr><w:rFonts w:ascii="Arial" w:eastAsia="楷体_GB2312" w:hAnsi="Arial"/></w:rPr></w:style><w:style w:type="paragraph" w:styleId="aff7"><w:name w:val="Plain Text"/><w:basedOn w:val="a5"/><w:link w:val="Charf9"/><w:uiPriority w:val="99"/><w:semiHidden/><w:unhideWhenUsed/><w:rsid w:val="005F4F81"/><w:rPr><w:rFonts w:ascii="宋体" w:eastAsia="宋体" w:hAnsi="Courier New" w:cs="Courier New"/><w:szCs w:val="21"/></w:rPr></w:style><w:style w:type="character" w:customStyle="1" w:styleId="Charf9"><w:name w:val="纯文本 Char"/><w:basedOn w:val="a6"/><w:link w:val="aff7"/><w:uiPriority w:val="99"/><w:semiHidden/><w:rsid w:val="005F4F81"/><w:rPr><w:rFonts w:ascii="宋体" w:eastAsia="宋体" w:hAnsi="Courier New" w:cs="Courier New"/><w:szCs w:val="21"/></w:rPr></w:style><w:style w:type="paragraph" w:styleId="aff8"><w:name w:val="E-mail Signature"/><w:basedOn w:val="a5"/><w:link w:val="Charfa"/><w:uiPriority w:val="99"/><w:semiHidden/><w:unhideWhenUsed/><w:rsid w:val="005F4F81"/></w:style><w:style w:type="character" w:customStyle="1" w:styleId="Charfa"><w:name w:val="电子邮件签名 Char"/><w:basedOn w:val="a6"/><w:link w:val="aff8"/><w:uiPriority w:val="99"/><w:semiHidden/><w:rsid w:val="005F4F81"/><w:rPr><w:rFonts w:ascii="Arial" w:eastAsia="楷体_GB2312" w:hAnsi="Arial"/></w:rPr></w:style><w:style w:type="paragraph" w:styleId="aff9"><w:name w:val="Subtitle"/><w:basedOn w:val="a5"/><w:next w:val="a5"/><w:link w:val="Charfb"/><w:uiPriority w:val="11"/><w:qFormat/><w:rsid w:val="005F4F81"/><w:pPr><w:spacing w:before="240" w:after="60" w:line="312" w:lineRule="auto"/><w:jc w:val="center"/><w:outlineLvl w:val="1"/></w:pPr><w:rPr><w:rFonts w:asciiTheme="majorHAnsi" w:eastAsia="宋体" w:hAnsiTheme="majorHAnsi" w:cstheme="majorBidi"/><w:b/><w:bCs/><w:kern w:val="28"/><w:sz w:val="32"/><w:szCs w:val="32"/></w:rPr></w:style><w:style w:type="character" w:customStyle="1" w:styleId="Charfb"><w:name w:val="副标题 Char"/><w:basedOn w:val="a6"/><w:link w:val="aff9"/><w:uiPriority w:val="11"/><w:rsid w:val="005F4F81"/><w:rPr><w:rFonts w:asciiTheme="majorHAnsi" w:eastAsia="宋体" w:hAnsiTheme="majorHAnsi" w:cstheme="majorBidi"/><w:b/><w:bCs/><w:kern w:val="28"/><w:sz w:val="32"/><w:szCs w:val="32"/></w:rPr></w:style><w:style w:type="paragraph" w:styleId="affa"><w:name w:val="macro"/><w:link w:val="Charfc"/><w:uiPriority w:val="99"/><w:semiHidden/><w:unhideWhenUsed/><w:rsid w:val="005F4F81"/><w:pPr><w:widowControl w:val="0"/><w:tabs><w:tab w:val="left" w:pos="480"/><w:tab w:val="left" w:pos="960"/><w:tab w:val="left" w:pos="1440"/><w:tab w:val="left" w:pos="1920"/><w:tab w:val="left" w:pos="2400"/><w:tab w:val="left" w:pos="2880"/><w:tab w:val="left" w:pos="3360"/><w:tab w:val="left" w:pos="3840"/><w:tab w:val="left" w:pos="4320"/></w:tabs><w:kinsoku w:val="0"/><w:overflowPunct w:val="0"/><w:autoSpaceDE w:val="0"/><w:autoSpaceDN w:val="0"/><w:snapToGrid w:val="0"/></w:pPr><w:rPr><w:rFonts w:ascii="Courier New" w:eastAsia="宋体" w:hAnsi="Courier New" w:cs="Courier New"/><w:sz w:val="24"/><w:szCs w:val="24"/></w:rPr></w:style><w:style w:type="character" w:customStyle="1" w:styleId="Charfc"><w:name w:val="宏文本 Char"/><w:basedOn w:val="a6"/><w:link w:val="affa"/><w:uiPriority w:val="99"/><w:semiHidden/><w:rsid w:val="005F4F81"/><w:rPr><w:rFonts w:ascii="Courier New" w:eastAsia="宋体" w:hAnsi="Courier New" w:cs="Courier New"/><w:sz w:val="24"/><w:szCs w:val="24"/></w:rPr></w:style><w:style w:type="paragraph" w:styleId="affb"><w:name w:val="envelope return"/><w:basedOn w:val="a5"/><w:uiPriority w:val="99"/><w:semiHidden/><w:unhideWhenUsed/><w:rsid w:val="005F4F81"/><w:pPr><w:snapToGrid w:val="0"/></w:pPr><w:rPr><w:rFonts w:asciiTheme="majorHAnsi" w:eastAsiaTheme="majorEastAsia" w:hAnsiTheme="majorHAnsi" w:cstheme="majorBidi"/></w:rPr></w:style><w:style w:type="paragraph" w:styleId="affc"><w:name w:val="footnote text"/><w:basedOn w:val="a5"/><w:link w:val="Charfd"/><w:uiPriority w:val="99"/><w:semiHidden/><w:unhideWhenUsed/><w:rsid w:val="005F4F81"/><w:pPr><w:snapToGrid w:val="0"/><w:jc w:val="left"/></w:pPr><w:rPr><w:sz w:val="18"/><w:szCs w:val="18"/></w:rPr></w:style><w:style w:type="character" w:customStyle="1" w:styleId="Charfd"><w:name w:val="脚注文本 Char"/><w:basedOn w:val="a6"/><w:link w:val="affc"/><w:uiPriority w:val="99"/><w:semiHidden/><w:rsid w:val="005F4F81"/><w:rPr><w:rFonts w:ascii="Arial" w:eastAsia="楷体_GB2312" w:hAnsi="Arial"/><w:sz w:val="18"/><w:szCs w:val="18"/></w:rPr></w:style><w:style w:type="paragraph" w:styleId="affd"><w:name w:val="Closing"/><w:basedOn w:val="a5"/><w:link w:val="Charfe"/><w:uiPriority w:val="99"/><w:semiHidden/><w:unhideWhenUsed/><w:rsid w:val="005F4F81"/><w:pPr><w:ind w:leftChars="2100" w:left="100"/></w:pPr></w:style><w:style w:type="character" w:customStyle="1" w:styleId="Charfe"><w:name w:val="结束语 Char"/><w:basedOn w:val="a6"/><w:link w:val="affd"/><w:uiPriority w:val="99"/><w:semiHidden/><w:rsid w:val="005F4F81"/><w:rPr><w:rFonts w:ascii="Arial" w:eastAsia="楷体_GB2312" w:hAnsi="Arial"/></w:rPr></w:style><w:style w:type="paragraph" w:styleId="affe"><w:name w:val="List"/><w:basedOn w:val="a5"/><w:uiPriority w:val="99"/><w:semiHidden/><w:unhideWhenUsed/><w:rsid w:val="005F4F81"/><w:pPr><w:ind w:left="200" w:hangingChars="200" w:hanging="200"/><w:contextualSpacing/></w:pPr></w:style><w:style w:type="paragraph" w:styleId="23"><w:name w:val="List 2"/><w:basedOn w:val="a5"/><w:uiPriority w:val="99"/><w:semiHidden/><w:unhideWhenUsed/><w:rsid w:val="005F4F81"/><w:pPr><w:ind w:leftChars="200" w:left="100" w:hangingChars="200" w:hanging="200"/><w:contextualSpacing/></w:pPr></w:style><w:style w:type="paragraph" w:styleId="32"><w:name w:val="List 3"/><w:basedOn w:val="a5"/><w:uiPriority w:val="99"/><w:semiHidden/><w:unhideWhenUsed/><w:rsid w:val="005F4F81"/><w:pPr><w:ind w:leftChars="400" w:left="100" w:hangingChars="200" w:hanging="200"/><w:contextualSpacing/></w:pPr></w:style><w:style w:type="paragraph" w:styleId="42"><w:name w:val="List 4"/><w:basedOn w:val="a5"/><w:uiPriority w:val="99"/><w:semiHidden/><w:unhideWhenUsed/><w:rsid w:val="005F4F81"/><w:pPr><w:ind w:leftChars="600" w:left="100" w:hangingChars="200" w:hanging="200"/><w:contextualSpacing/></w:pPr></w:style><w:style w:type="paragraph" w:styleId="52"><w:name w:val="List 5"/><w:basedOn w:val="a5"/><w:uiPriority w:val="99"/><w:semiHidden/><w:unhideWhenUsed/><w:rsid w:val="005F4F81"/><w:pPr><w:ind w:leftChars="800" w:left="100" w:hangingChars="200" w:hanging="200"/><w:contextualSpacing/></w:pPr></w:style><w:style w:type="paragraph" w:styleId="a"><w:name w:val="List Number"/><w:basedOn w:val="a5"/><w:uiPriority w:val="99"/><w:semiHidden/><w:unhideWhenUsed/><w:rsid w:val="005F4F81"/><w:pPr><w:numPr><w:numId w:val="8"/></w:numPr><w:contextualSpacing/></w:pPr></w:style><w:style w:type="paragraph" w:styleId="2"><w:name w:val="List Number 2"/><w:basedOn w:val="a5"/><w:uiPriority w:val="99"/><w:semiHidden/><w:unhideWhenUsed/><w:rsid w:val="005F4F81"/><w:pPr><w:numPr><w:numId w:val="9"/></w:numPr><w:contextualSpacing/></w:pPr></w:style><w:style w:type="paragraph" w:styleId="3"><w:name w:val="List Number 3"/><w:basedOn w:val="a5"/><w:uiPriority w:val="99"/><w:semiHidden/><w:unhideWhenUsed/><w:rsid w:val="005F4F81"/><w:pPr><w:numPr><w:numId w:val="10"/></w:numPr><w:contextualSpacing/></w:pPr></w:style><w:style w:type="paragraph" w:styleId="4"><w:name w:val="List Number 4"/><w:basedOn w:val="a5"/><w:uiPriority w:val="99"/><w:semiHidden/><w:unhideWhenUsed/><w:rsid w:val="005F4F81"/><w:pPr><w:numPr><w:numId w:val="11"/></w:numPr><w:contextualSpacing/></w:pPr></w:style><w:style w:type="paragraph" w:styleId="5"><w:name w:val="List Number 5"/><w:basedOn w:val="a5"/><w:uiPriority w:val="99"/><w:semiHidden/><w:unhideWhenUsed/><w:rsid w:val="005F4F81"/><w:pPr><w:numPr><w:numId w:val="12"/></w:numPr><w:contextualSpacing/></w:pPr></w:style><w:style w:type="paragraph" w:styleId="afff"><w:name w:val="List Continue"/><w:basedOn w:val="a5"/><w:uiPriority w:val="99"/><w:semiHidden/><w:unhideWhenUsed/><w:rsid w:val="005F4F81"/><w:pPr><w:spacing w:after="120"/><w:ind w:leftChars="200" w:left="420"/><w:contextualSpacing/></w:pPr></w:style><w:style w:type="paragraph" w:styleId="24"><w:name w:val="List Continue 2"/><w:basedOn w:val="a5"/><w:uiPriority w:val="99"/><w:semiHidden/><w:unhideWhenUsed/><w:rsid w:val="005F4F81"/><w:pPr><w:spacing w:after="120"/><w:ind w:leftChars="400" w:left="840"/><w:contextualSpacing/></w:pPr></w:style><w:style w:type="paragraph" w:styleId="33"><w:name w:val="List Continue 3"/><w:basedOn w:val="a5"/><w:uiPriority w:val="99"/><w:semiHidden/><w:unhideWhenUsed/><w:rsid w:val="005F4F81"/><w:pPr><w:spacing w:after="120"/><w:ind w:leftChars="600" w:left="1260"/><w:contextualSpacing/></w:pPr></w:style><w:style w:type="paragraph" w:styleId="43"><w:name w:val="List Continue 4"/><w:basedOn w:val="a5"/><w:uiPriority w:val="99"/><w:semiHidden/><w:unhideWhenUsed/><w:rsid w:val="005F4F81"/><w:pPr><w:spacing w:after="120"/><w:ind w:leftChars="800" w:left="1680"/><w:contextualSpacing/></w:pPr></w:style><w:style w:type="paragraph" w:styleId="53"><w:name w:val="List Continue 5"/><w:basedOn w:val="a5"/><w:uiPriority w:val="99"/><w:semiHidden/><w:unhideWhenUsed/><w:rsid w:val="005F4F81"/><w:pPr><w:spacing w:after="120"/><w:ind w:leftChars="1000" w:left="2100"/><w:contextualSpacing/></w:pPr></w:style><w:style w:type="paragraph" w:styleId="a0"><w:name w:val="List Bullet"/><w:basedOn w:val="a5"/><w:uiPriority w:val="99"/><w:semiHidden/><w:unhideWhenUsed/><w:rsid w:val="005F4F81"/><w:pPr><w:numPr><w:numId w:val="13"/></w:numPr><w:contextualSpacing/></w:pPr></w:style><w:style w:type="paragraph" w:styleId="20"><w:name w:val="List Bullet 2"/><w:basedOn w:val="a5"/><w:uiPriority w:val="99"/><w:semiHidden/><w:unhideWhenUsed/><w:rsid w:val="005F4F81"/><w:pPr><w:numPr><w:numId w:val="14"/></w:numPr><w:contextualSpacing/></w:pPr></w:style><w:style w:type="paragraph" w:styleId="30"><w:name w:val="List Bullet 3"/><w:basedOn w:val="a5"/><w:uiPriority w:val="99"/><w:semiHidden/><w:unhideWhenUsed/><w:rsid w:val="005F4F81"/><w:pPr><w:numPr><w:numId w:val="15"/></w:numPr><w:contextualSpacing/></w:pPr></w:style><w:style w:type="paragraph" w:styleId="40"><w:name w:val="List Bullet 4"/><w:basedOn w:val="a5"/><w:uiPriority w:val="99"/><w:semiHidden/><w:unhideWhenUsed/><w:rsid w:val="005F4F81"/><w:pPr><w:numPr><w:numId w:val="16"/></w:numPr><w:contextualSpacing/></w:pPr></w:style><w:style w:type="paragraph" w:styleId="50"><w:name w:val="List Bullet 5"/><w:basedOn w:val="a5"/><w:uiPriority w:val="99"/><w:semiHidden/><w:unhideWhenUsed/><w:rsid w:val="005F4F81"/><w:pPr><w:numPr><w:numId w:val="17"/></w:numPr><w:contextualSpacing/></w:pPr></w:style><w:style w:type="paragraph" w:styleId="afff0"><w:name w:val="Intense Quote"/><w:basedOn w:val="a5"/><w:next w:val="a5"/><w:link w:val="Charff"/><w:uiPriority w:val="30"/><w:qFormat/><w:rsid w:val="005F4F81"/><w:pPr><w:pBdr><w:top w:val="single" w:sz="4" w:space="10" w:color="5B9BD5" w:themeColor="accent1"/><w:bottom w:val="single" w:sz="4" w:space="10" w:color="5B9BD5" w:themeColor="accent1"/></w:pBdr><w:spacing w:before="360" w:after="360"/><w:ind w:left="864" w:right="864"/><w:jc w:val="center"/></w:pPr><w:rPr><w:i/><w:iCs/><w:color w:val="5B9BD5" w:themeColor="accent1"/></w:rPr></w:style><w:style w:type="character" w:customStyle="1" w:styleId="Charff"><w:name w:val="明显引用 Char"/><w:basedOn w:val="a6"/><w:link w:val="afff0"/><w:uiPriority w:val="30"/><w:rsid w:val="005F4F81"/><w:rPr><w:rFonts w:ascii="Arial" w:eastAsia="楷体_GB2312" w:hAnsi="Arial"/><w:i/><w:iCs/><w:color w:val="5B9BD5" w:themeColor="accent1"/></w:rPr></w:style><w:style w:type="paragraph" w:styleId="34"><w:name w:val="toc 3"/><w:basedOn w:val="a5"/><w:next w:val="a5"/><w:autoRedefine/><w:uiPriority w:val="39"/><w:semiHidden/><w:unhideWhenUsed/><w:rsid w:val="005F4F81"/><w:pPr><w:ind w:leftChars="400" w:left="840"/></w:pPr></w:style><w:style w:type="paragraph" w:styleId="44"><w:name w:val="toc 4"/><w:basedOn w:val="a5"/><w:next w:val="a5"/><w:autoRedefine/><w:uiPriority w:val="39"/><w:semiHidden/><w:unhideWhenUsed/><w:rsid w:val="005F4F81"/><w:pPr><w:ind w:leftChars="600" w:left="1260"/></w:pPr></w:style><w:style w:type="paragraph" w:styleId="54"><w:name w:val="toc 5"/><w:basedOn w:val="a5"/><w:next w:val="a5"/><w:autoRedefine/><w:uiPriority w:val="39"/><w:semiHidden/><w:unhideWhenUsed/><w:rsid w:val="005F4F81"/><w:pPr><w:ind w:leftChars="800" w:left="1680"/></w:pPr></w:style><w:style w:type="paragraph" w:styleId="60"><w:name w:val="toc 6"/><w:basedOn w:val="a5"/><w:next w:val="a5"/><w:autoRedefine/><w:uiPriority w:val="39"/><w:semiHidden/><w:unhideWhenUsed/><w:rsid w:val="005F4F81"/><w:pPr><w:ind w:leftChars="1000" w:left="2100"/></w:pPr></w:style><w:style w:type="paragraph" w:styleId="70"><w:name w:val="toc 7"/><w:basedOn w:val="a5"/><w:next w:val="a5"/><w:autoRedefine/><w:uiPriority w:val="39"/><w:semiHidden/><w:unhideWhenUsed/><w:rsid w:val="005F4F81"/><w:pPr><w:ind w:leftChars="1200" w:left="2520"/></w:pPr></w:style><w:style w:type="paragraph" w:styleId="80"><w:name w:val="toc 8"/><w:basedOn w:val="a5"/><w:next w:val="a5"/><w:autoRedefine/><w:uiPriority w:val="39"/><w:semiHidden/><w:unhideWhenUsed/><w:rsid w:val="005F4F81"/><w:pPr><w:ind w:leftChars="1400" w:left="2940"/></w:pPr></w:style><w:style w:type="paragraph" w:styleId="90"><w:name w:val="toc 9"/><w:basedOn w:val="a5"/><w:next w:val="a5"/><w:autoRedefine/><w:uiPriority w:val="39"/><w:semiHidden/><w:unhideWhenUsed/><w:rsid w:val="005F4F81"/><w:pPr><w:ind w:leftChars="1600" w:left="3360"/></w:pPr></w:style><w:style w:type="paragraph" w:styleId="afff1"><w:name w:val="Normal (Web)"/><w:basedOn w:val="a5"/><w:uiPriority w:val="99"/><w:unhideWhenUsed/><w:qFormat/><w:rsid w:val="005F4F81"/><w:rPr><w:rFonts w:ascii="Times New Roman" w:hAnsi="Times New Roman" w:cs="Times New Roman"/><w:sz w:val="24"/><w:szCs w:val="24"/></w:rPr></w:style><w:style w:type="paragraph" w:styleId="afff2"><w:name w:val="Signature"/><w:basedOn w:val="a5"/><w:link w:val="Charff0"/><w:uiPriority w:val="99"/><w:semiHidden/><w:unhideWhenUsed/><w:rsid w:val="005F4F81"/><w:pPr><w:ind w:leftChars="2100" w:left="100"/></w:pPr></w:style><w:style w:type="character" w:customStyle="1" w:styleId="Charff0"><w:name w:val="签名 Char"/><w:basedOn w:val="a6"/><w:link w:val="afff2"/><w:uiPriority w:val="99"/><w:semiHidden/><w:rsid w:val="005F4F81"/><w:rPr><w:rFonts w:ascii="Arial" w:eastAsia="楷体_GB2312" w:hAnsi="Arial"/></w:rPr></w:style><w:style w:type="paragraph" w:styleId="afff3"><w:name w:val="Date"/><w:basedOn w:val="a5"/><w:next w:val="a5"/><w:link w:val="Charff1"/><w:uiPriority w:val="99"/><w:semiHidden/><w:unhideWhenUsed/><w:rsid w:val="005F4F81"/><w:pPr><w:ind w:leftChars="2500" w:left="100"/></w:pPr></w:style><w:style w:type="character" w:customStyle="1" w:styleId="Charff1"><w:name w:val="日期 Char"/><w:basedOn w:val="a6"/><w:link w:val="afff3"/><w:uiPriority w:val="99"/><w:semiHidden/><w:rsid w:val="005F4F81"/><w:rPr><w:rFonts w:ascii="Arial" w:eastAsia="楷体_GB2312" w:hAnsi="Arial"/></w:rPr></w:style><w:style w:type="paragraph" w:styleId="afff4"><w:name w:val="envelope address"/><w:basedOn w:val="a5"/><w:uiPriority w:val="99"/><w:semiHidden/><w:unhideWhenUsed/><w:rsid w:val="005F4F81"/><w:pPr><w:framePr w:w="7920" w:h="1980" w:hRule="exact" w:hSpace="180" w:wrap="auto" w:hAnchor="page" w:xAlign="center" w:yAlign="bottom"/><w:snapToGrid w:val="0"/><w:ind w:leftChars="1400" w:left="100"/></w:pPr><w:rPr><w:rFonts w:asciiTheme="majorHAnsi" w:eastAsiaTheme="majorEastAsia" w:hAnsiTheme="majorHAnsi" w:cstheme="majorBidi"/><w:sz w:val="24"/><w:szCs w:val="24"/></w:rPr></w:style><w:style w:type="paragraph" w:styleId="afff5"><w:name w:val="Bibliography"/><w:basedOn w:val="a5"/><w:next w:val="a5"/><w:uiPriority w:val="37"/><w:semiHidden/><w:unhideWhenUsed/><w:rsid w:val="005F4F81"/></w:style><w:style w:type="paragraph" w:styleId="11"><w:name w:val="index 1"/><w:basedOn w:val="a5"/><w:next w:val="a5"/><w:autoRedefine/><w:uiPriority w:val="99"/><w:semiHidden/><w:unhideWhenUsed/><w:rsid w:val="005F4F81"/></w:style><w:style w:type="paragraph" w:styleId="25"><w:name w:val="index 2"/><w:basedOn w:val="a5"/><w:next w:val="a5"/><w:autoRedefine/><w:uiPriority w:val="99"/><w:semiHidden/><w:unhideWhenUsed/><w:rsid w:val="005F4F81"/><w:pPr><w:ind w:leftChars="200" w:left="200"/></w:pPr></w:style><w:style w:type="paragraph" w:styleId="35"><w:name w:val="index 3"/><w:basedOn w:val="a5"/><w:next w:val="a5"/><w:autoRedefine/><w:uiPriority w:val="99"/><w:semiHidden/><w:unhideWhenUsed/><w:rsid w:val="005F4F81"/><w:pPr><w:ind w:leftChars="400" w:left="400"/></w:pPr></w:style><w:style w:type="paragraph" w:styleId="45"><w:name w:val="index 4"/><w:basedOn w:val="a5"/><w:next w:val="a5"/><w:autoRedefine/><w:uiPriority w:val="99"/><w:semiHidden/><w:unhideWhenUsed/><w:rsid w:val="005F4F81"/><w:pPr><w:ind w:leftChars="600" w:left="600"/></w:pPr></w:style><w:style w:type="paragraph" w:styleId="55"><w:name w:val="index 5"/><w:basedOn w:val="a5"/><w:next w:val="a5"/><w:autoRedefine/><w:uiPriority w:val="99"/><w:semiHidden/><w:unhideWhenUsed/><w:rsid w:val="005F4F81"/><w:pPr><w:ind w:leftChars="800" w:left="800"/></w:pPr></w:style><w:style w:type="paragraph" w:styleId="61"><w:name w:val="index 6"/><w:basedOn w:val="a5"/><w:next w:val="a5"/><w:autoRedefine/><w:uiPriority w:val="99"/><w:semiHidden/><w:unhideWhenUsed/><w:rsid w:val="005F4F81"/><w:pPr><w:ind w:leftChars="1000" w:left="1000"/></w:pPr></w:style><w:style w:type="paragraph" w:styleId="71"><w:name w:val="index 7"/><w:basedOn w:val="a5"/><w:next w:val="a5"/><w:autoRedefine/><w:uiPriority w:val="99"/><w:semiHidden/><w:unhideWhenUsed/><w:rsid w:val="005F4F81"/><w:pPr><w:ind w:leftChars="1200" w:left="1200"/></w:pPr></w:style><w:style w:type="paragraph" w:styleId="81"><w:name w:val="index 8"/><w:basedOn w:val="a5"/><w:next w:val="a5"/><w:autoRedefine/><w:uiPriority w:val="99"/><w:semiHidden/><w:unhideWhenUsed/><w:rsid w:val="005F4F81"/><w:pPr><w:ind w:leftChars="1400" w:left="1400"/></w:pPr></w:style><w:style w:type="paragraph" w:styleId="91"><w:name w:val="index 9"/><w:basedOn w:val="a5"/><w:next w:val="a5"/><w:autoRedefine/><w:uiPriority w:val="99"/><w:semiHidden/><w:unhideWhenUsed/><w:rsid w:val="005F4F81"/><w:pPr><w:ind w:leftChars="1600" w:left="1600"/></w:pPr></w:style><w:style w:type="paragraph" w:styleId="afff6"><w:name w:val="index heading"/><w:basedOn w:val="a5"/><w:next w:val="11"/><w:uiPriority w:val="99"/><w:semiHidden/><w:unhideWhenUsed/><w:rsid w:val="005F4F81"/><w:rPr><w:rFonts w:asciiTheme="majorHAnsi" w:eastAsiaTheme="majorEastAsia" w:hAnsiTheme="majorHAnsi" w:cstheme="majorBidi"/><w:b/><w:bCs/></w:rPr></w:style><w:style w:type="paragraph" w:styleId="afff7"><w:name w:val="endnote text"/><w:basedOn w:val="a5"/><w:link w:val="Charff2"/><w:uiPriority w:val="99"/><w:semiHidden/><w:unhideWhenUsed/><w:rsid w:val="005F4F81"/><w:pPr><w:snapToGrid w:val="0"/><w:jc w:val="left"/></w:pPr></w:style><w:style w:type="character" w:customStyle="1" w:styleId="Charff2"><w:name w:val="尾注文本 Char"/><w:basedOn w:val="a6"/><w:link w:val="afff7"/><w:uiPriority w:val="99"/><w:semiHidden/><w:rsid w:val="005F4F81"/><w:rPr><w:rFonts w:ascii="Arial" w:eastAsia="楷体_GB2312" w:hAnsi="Arial"/></w:rPr></w:style><w:style w:type="paragraph" w:styleId="afff8"><w:name w:val="Block Text"/><w:basedOn w:val="a5"/><w:uiPriority w:val="99"/><w:semiHidden/><w:unhideWhenUsed/><w:rsid w:val="005F4F81"/><w:pPr><w:spacing w:after="120"/><w:ind w:leftChars="700" w:left="1440" w:rightChars="700" w:right="1440"/></w:pPr></w:style><w:style w:type="paragraph" w:styleId="afff9"><w:name w:val="Document Map"/><w:basedOn w:val="a5"/><w:link w:val="Charff3"/><w:uiPriority w:val="99"/><w:semiHidden/><w:unhideWhenUsed/><w:rsid w:val="005F4F81"/><w:rPr><w:rFonts w:ascii="Microsoft YaHei UI" w:eastAsia="Microsoft YaHei UI"/><w:sz w:val="18"/><w:szCs w:val="18"/></w:rPr></w:style><w:style w:type="character" w:customStyle="1" w:styleId="Charff3"><w:name w:val="文档结构图 Char"/><w:basedOn w:val="a6"/><w:link w:val="afff9"/><w:uiPriority w:val="99"/><w:semiHidden/><w:rsid w:val="005F4F81"/><w:rPr><w:rFonts w:ascii="Microsoft YaHei UI" w:eastAsia="Microsoft YaHei UI" w:hAnsi="Arial"/><w:sz w:val="18"/><w:szCs w:val="18"/></w:rPr></w:style><w:style w:type="paragraph" w:styleId="afffa"><w:name w:val="No Spacing"/><w:uiPriority w:val="1"/><w:qFormat/><w:rsid w:val="000719A8"/><w:pPr><w:widowControl w:val="0"/><w:jc w:val="both"/></w:pPr><w:rPr><w:rFonts w:ascii="Arial" w:eastAsia="楷体" w:hAnsi="Arial"/></w:rPr></w:style><w:style w:type="paragraph" w:styleId="afffb"><w:name w:val="Message Header"/><w:basedOn w:val="a5"/><w:link w:val="Charff4"/><w:uiPriority w:val="99"/><w:semiHidden/><w:unhideWhenUsed/><w:rsid w:val="005F4F81"/><w:pPr><w:pBdr><w:top w:val="single" w:sz="6" w:space="1" w:color="auto"/><w:left w:val="single" w:sz="6" w:space="1" w:color="auto"/><w:bottom w:val="single" w:sz="6" w:space="1" w:color="auto"/><w:right w:val="single" w:sz="6" w:space="1" w:color="auto"/></w:pBdr><w:shd w:val="pct20" w:color="auto" w:fill="auto"/><w:ind w:leftChars="500" w:left="1080" w:hangingChars="500" w:hanging="1080"/></w:pPr><w:rPr><w:rFonts w:asciiTheme="majorHAnsi" w:eastAsiaTheme="majorEastAsia" w:hAnsiTheme="majorHAnsi" w:cstheme="majorBidi"/><w:sz w:val="24"/><w:szCs w:val="24"/></w:rPr></w:style><w:style w:type="character" w:customStyle="1" w:styleId="Charff4"><w:name w:val="信息标题 Char"/><w:basedOn w:val="a6"/><w:link w:val="afffb"/><w:uiPriority w:val="99"/><w:semiHidden/><w:rsid w:val="005F4F81"/><w:rPr><w:rFonts w:asciiTheme="majorHAnsi" w:eastAsiaTheme="majorEastAsia" w:hAnsiTheme="majorHAnsi" w:cstheme="majorBidi"/><w:sz w:val="24"/><w:szCs w:val="24"/><w:shd w:val="pct20" w:color="auto" w:fill="auto"/></w:rPr></w:style><w:style w:type="paragraph" w:styleId="afffc"><w:name w:val="table of authorities"/><w:basedOn w:val="a5"/><w:next w:val="a5"/><w:uiPriority w:val="99"/><w:semiHidden/><w:unhideWhenUsed/><w:rsid w:val="005F4F81"/><w:pPr><w:ind w:leftChars="200" w:left="420"/></w:pPr></w:style><w:style w:type="paragraph" w:styleId="afffd"><w:name w:val="toa heading"/><w:basedOn w:val="a5"/><w:next w:val="a5"/><w:uiPriority w:val="99"/><w:semiHidden/><w:unhideWhenUsed/><w:rsid w:val="005F4F81"/><w:pPr><w:spacing w:before="120"/></w:pPr><w:rPr><w:rFonts w:asciiTheme="majorHAnsi" w:eastAsia="宋体" w:hAnsiTheme="majorHAnsi" w:cstheme="majorBidi"/><w:sz w:val="24"/><w:szCs w:val="24"/></w:rPr></w:style><w:style w:type="paragraph" w:styleId="afffe"><w:name w:val="Quote"/><w:basedOn w:val="a5"/><w:next w:val="a5"/><w:link w:val="Charff5"/><w:uiPriority w:val="29"/><w:qFormat/><w:rsid w:val="005F4F81"/><w:pPr><w:spacing w:before="200" w:after="160"/><w:ind w:left="864" w:right="864"/><w:jc w:val="center"/></w:pPr><w:rPr><w:i/><w:iCs/><w:color w:val="404040" w:themeColor="text1" w:themeTint="BF"/></w:rPr></w:style><w:style w:type="character" w:customStyle="1" w:styleId="Charff5"><w:name w:val="引用 Char"/><w:basedOn w:val="a6"/><w:link w:val="afffe"/><w:uiPriority w:val="29"/><w:rsid w:val="005F4F81"/><w:rPr><w:rFonts w:ascii="Arial" w:eastAsia="楷体_GB2312" w:hAnsi="Arial"/><w:i/><w:iCs/><w:color w:val="404040" w:themeColor="text1" w:themeTint="BF"/></w:rPr></w:style><w:style w:type="paragraph" w:styleId="affff"><w:name w:val="Body Text First Indent"/><w:basedOn w:val="afe"/><w:link w:val="Charff6"/><w:uiPriority w:val="99"/><w:semiHidden/><w:unhideWhenUsed/><w:rsid w:val="005F4F81"/><w:pPr><w:ind w:firstLineChars="100" w:firstLine="420"/></w:pPr></w:style><w:style w:type="character" w:customStyle="1" w:styleId="Charff6"><w:name w:val="正文首行缩进 Char"/><w:basedOn w:val="Charf3"/><w:link w:val="affff"/><w:uiPriority w:val="99"/><w:semiHidden/><w:rsid w:val="005F4F81"/><w:rPr><w:rFonts w:ascii="Arial" w:eastAsia="楷体_GB2312" w:hAnsi="Arial"/></w:rPr></w:style><w:style w:type="paragraph" w:styleId="affff0"><w:name w:val="Body Text Indent"/><w:basedOn w:val="a5"/><w:link w:val="Charff7"/><w:uiPriority w:val="99"/><w:semiHidden/><w:unhideWhenUsed/><w:rsid w:val="005F4F81"/><w:pPr><w:spacing w:after="120"/><w:ind w:leftChars="200" w:left="420"/></w:pPr></w:style><w:style w:type="character" w:customStyle="1" w:styleId="Charff7"><w:name w:val="正文文本缩进 Char"/><w:basedOn w:val="a6"/><w:link w:val="affff0"/><w:uiPriority w:val="99"/><w:semiHidden/><w:rsid w:val="005F4F81"/><w:rPr><w:rFonts w:ascii="Arial" w:eastAsia="楷体_GB2312" w:hAnsi="Arial"/></w:rPr></w:style><w:style w:type="paragraph" w:styleId="26"><w:name w:val="Body Text First Indent 2"/><w:basedOn w:val="affff0"/><w:link w:val="2Char0"/><w:uiPriority w:val="99"/><w:semiHidden/><w:unhideWhenUsed/><w:rsid w:val="005F4F81"/><w:pPr><w:ind w:firstLineChars="200" w:firstLine="420"/></w:pPr></w:style><w:style w:type="character" w:customStyle="1" w:styleId="2Char0"><w:name w:val="正文首行缩进 2 Char"/><w:basedOn w:val="Charff7"/><w:link w:val="26"/><w:uiPriority w:val="99"/><w:semiHidden/><w:rsid w:val="005F4F81"/><w:rPr><w:rFonts w:ascii="Arial" w:eastAsia="楷体_GB2312" w:hAnsi="Arial"/></w:rPr></w:style><w:style w:type="paragraph" w:styleId="affff1"><w:name w:val="Normal Indent"/><w:basedOn w:val="a5"/><w:uiPriority w:val="99"/><w:semiHidden/><w:unhideWhenUsed/><w:rsid w:val="005F4F81"/><w:pPr><w:ind w:firstLineChars="200" w:firstLine="420"/></w:pPr></w:style><w:style w:type="paragraph" w:styleId="27"><w:name w:val="Body Text 2"/><w:basedOn w:val="a5"/><w:link w:val="2Char1"/><w:uiPriority w:val="99"/><w:semiHidden/><w:unhideWhenUsed/><w:rsid w:val="005F4F81"/><w:pPr><w:spacing w:after="120" w:line="480" w:lineRule="auto"/></w:pPr></w:style><w:style w:type="character" w:customStyle="1" w:styleId="2Char1"><w:name w:val="正文文本 2 Char"/><w:basedOn w:val="a6"/><w:link w:val="27"/><w:uiPriority w:val="99"/><w:semiHidden/><w:rsid w:val="005F4F81"/><w:rPr><w:rFonts w:ascii="Arial" w:eastAsia="楷体_GB2312" w:hAnsi="Arial"/></w:rPr></w:style><w:style w:type="paragraph" w:styleId="36"><w:name w:val="Body Text 3"/><w:basedOn w:val="a5"/><w:link w:val="3Char0"/><w:uiPriority w:val="99"/><w:semiHidden/><w:unhideWhenUsed/><w:rsid w:val="005F4F81"/><w:pPr><w:spacing w:after="120"/></w:pPr><w:rPr><w:sz w:val="16"/><w:szCs w:val="16"/></w:rPr></w:style><w:style w:type="character" w:customStyle="1" w:styleId="3Char0"><w:name w:val="正文文本 3 Char"/><w:basedOn w:val="a6"/><w:link w:val="36"/><w:uiPriority w:val="99"/><w:semiHidden/><w:rsid w:val="005F4F81"/><w:rPr><w:rFonts w:ascii="Arial" w:eastAsia="楷体_GB2312" w:hAnsi="Arial"/><w:sz w:val="16"/><w:szCs w:val="16"/></w:rPr></w:style><w:style w:type="paragraph" w:styleId="28"><w:name w:val="Body Text Indent 2"/><w:basedOn w:val="a5"/><w:link w:val="2Char2"/><w:uiPriority w:val="99"/><w:semiHidden/><w:unhideWhenUsed/><w:rsid w:val="005F4F81"/><w:pPr><w:spacing w:after="120" w:line="480" w:lineRule="auto"/><w:ind w:leftChars="200" w:left="420"/></w:pPr></w:style><w:style w:type="character" w:customStyle="1" w:styleId="2Char2"><w:name w:val="正文文本缩进 2 Char"/><w:basedOn w:val="a6"/><w:link w:val="28"/><w:uiPriority w:val="99"/><w:semiHidden/><w:rsid w:val="005F4F81"/><w:rPr><w:rFonts w:ascii="Arial" w:eastAsia="楷体_GB2312" w:hAnsi="Arial"/></w:rPr></w:style><w:style w:type="paragraph" w:styleId="37"><w:name w:val="Body Text Indent 3"/><w:basedOn w:val="a5"/><w:link w:val="3Char1"/><w:uiPriority w:val="99"/><w:semiHidden/><w:unhideWhenUsed/><w:rsid w:val="005F4F81"/><w:pPr><w:spacing w:after="120"/><w:ind w:leftChars="200" w:left="420"/></w:pPr><w:rPr><w:sz w:val="16"/><w:szCs w:val="16"/></w:rPr></w:style><w:style w:type="character" w:customStyle="1" w:styleId="3Char1"><w:name w:val="正文文本缩进 3 Char"/><w:basedOn w:val="a6"/><w:link w:val="37"/><w:uiPriority w:val="99"/><w:semiHidden/><w:rsid w:val="005F4F81"/><w:rPr><w:rFonts w:ascii="Arial" w:eastAsia="楷体_GB2312" w:hAnsi="Arial"/><w:sz w:val="16"/><w:szCs w:val="16"/></w:rPr></w:style><w:style w:type="paragraph" w:styleId="affff2"><w:name w:val="Note Heading"/><w:basedOn w:val="a5"/><w:next w:val="a5"/><w:link w:val="Charff8"/><w:uiPriority w:val="99"/><w:semiHidden/><w:unhideWhenUsed/><w:rsid w:val="005F4F81"/><w:pPr><w:jc w:val="center"/></w:pPr></w:style><w:style w:type="character" w:customStyle="1" w:styleId="Charff8"><w:name w:val="注释标题 Char"/><w:basedOn w:val="a6"/><w:link w:val="affff2"/><w:uiPriority w:val="99"/><w:semiHidden/><w:rsid w:val="005F4F81"/><w:rPr><w:rFonts w:ascii="Arial" w:eastAsia="楷体_GB2312" w:hAnsi="Arial"/></w:rPr></w:style><w:style w:type="character" w:styleId="affff3"><w:name w:val="Strong"/><w:basedOn w:val="a6"/><w:uiPriority w:val="22"/><w:qFormat/><w:rsid w:val="00F34556"/><w:rPr><w:b/><w:bCs/></w:rPr></w:style></w:styles>